{
  "records": {
    "20260314093233": [
      "生物",
      "积累",
      "知识点::生物::生态系统::食物链与食物网::营养级",
      "知识点::生物::生态系统::能量流动",
      "题型::选择题::单项选择题::高考真题",
      "难度::基础::概念辨析类",
      "能力素养::生物::科学思维::概念判断",
      "能力素养::生物::生命观念::生态观"
    ],
    "20260314093607": [
      "生物",
      "积累",
      "能力素养::生物::科学思维::信息提取与判断",
      "知识点::生物::生态与环境::环境胁迫",
      "知识点::生物::种群::环境容纳量",
      "知识点::生物::生态系统::生物富集作用",
      "知识点::生物::生命活动调节::稳态调节",
      "题型::高考真题::2023湖北卷",
      "难度::中档::概念辨析类",
      "能力素养::生物::生命观念::稳态与平衡观",
      "题型::选择题::单项选择题"
    ],
    "20260314094138": [
      "生物",
      "积累",
      "能力素养::生物::科学思维::信息提取与计算",
      "能力素养::生物::生命观念::能量观",
      "知识点::生物::生态系统::能量流动::生长发育繁殖能量计算",
      "难度::中档::数据计算类",
      "知识点::生物::生态系统::能量流动::同化量与摄入量关系",
      "知识点::生物::生态系统::能量流动::流经生态系统总能量判断",
      "题型::选择题::单项选择题::图表信息类",
      "知识点::生物::生态系统::能量流动::能量传递效率计算",
      "知识点::生物::生态系统::能量流动::粪便能量归属"
    ],
    "20260314095924": [
      "生物",
      "积累",
      "知识点::生物::稳态与环境::生态系统::能量流动",
      "知识点::生物::稳态与环境::生物多样性::间接价值",
      "难度::基础::概念辨析类",
      "知识点::生物::稳态与环境::生态系统稳定性",
      "题型::选择题::单项选择题::选考真题",
      "知识点::生物::稳态与环境::生态系统::生态系统的结构",
      "能力素养::生物::科学思维::分析判断",
      "能力素养::生物::生命观念::生态观"
    ],
    "20260314095936": [
      "生物",
      "积累",
      "知识点::生物::必修三::生态系统::生态系统稳定性",
      "知识点::生物::必修三::生态系统保护",
      "知识点::生物::必修三::生物多样性::协同进化",
      "题型::选择题::单项选择题::高考真题",
      "难度::基础::概念辨析类",
      "能力素养::生物::生命观念::稳态与平衡观",
      "知识点::生物::必修三::种间关系::互利共生",
      "能力素养::生物::科学思维::概念辨析"
    ],
    "20260314095948": [
      "生物",
      "积累",
      "知识点::生物::稳态与环境::生态系统::能量流动",
      "知识点::生物::稳态与环境::种间关系",
      "知识点::生物::稳态与环境::生态系统::信息传递",
      "题型::选择题::单项选择题::高考真题",
      "难度::基础::概念辨析类",
      "能力素养::生物::科学思维::概念判断",
      "知识点::生物::稳态与环境::生态系统::物质循环",
      "能力素养::生物::生命观念::生态观"
    ],
    "20260314095959": [
      "生物",
      "积累",
      "知识点::生物::生态学::种群的特征",
      "知识点::生物::生态学::生态系统的功能",
      "难度::基础::概念辨析类",
      "知识点::生物::生态学::群落演替",
      "能力素养::生物::生命观念::稳态与平衡观",
      "能力素养::生物::科学思维::概念辨析",
      "知识点::生物::生态学::可持续发展",
      "题型::选择题::单项选择题::正误判断类"
    ],
    "20260314100019": [
      "生物",
      "积累",
      "知识点::生物::生态农业::原理应用",
      "知识点::生物::生态系统::物质循环",
      "知识点::生物::群落::群落空间结构",
      "知识点::生物::生态系统::能量流动",
      "题型::选择题::单项选择题::高考真题",
      "难度::中档::多考点综合",
      "能力素养::生物::科学思维::逻辑推理",
      "能力素养::生物::生命观念::生态观"
    ],
    "20260314100032": [
      "生物",
      "积累",
      "题型::高考真题::天津卷::2022年",
      "知识点::生物::生态学::生态系统的功能::物质循环与能量流动",
      "难度::基础::概念辨析类",
      "能力素养::生物::生命观念::稳态与平衡观",
      "能力素养::生物::科学思维::概念辨析",
      "知识点::生物::生态学::生态系统保护::生态工程原理",
      "题型::选择题::单项选择题::正误判断类",
      "知识点::生物::生态学::生态系统的稳定性::自我调节能力"
    ],
    "20260314100044": [
      "生物",
      "积累",
      "知识点::生物::生态系统::能量流动的特点",
      "能力素养::生物::生命观念::物质能量观",
      "知识点::生物::生态系统::物质循环",
      "知识点::生物::生态系统组成成分::分解者",
      "题型::选择题::单项选择题::高考真题",
      "难度::基础::概念辨析类",
      "能力素养::生物::思维::概念判断",
      "知识点::生物::生态保护::植被水土保持作用"
    ],
    "20260314100056": [
      "生物",
      "积累",
      "知识点::生物::生态农业::管理措施效益分析",
      "知识点::生物::光合作用::影响光合作用的环境因素",
      "知识点::生物::害虫防治::生物防治",
      "知识点::生物::生态系统::物质循环",
      "知识点::生物::生态系统::能量流动::能量传递效率与利用率辨析",
      "难度::基础::概念辨析类",
      "能力素养::生物::科学思维::概念辨析",
      "题型::选择题::高考真题",
      "题型::选择题::单项选择题::正误判断类",
      "能力素养::生物::生命观念::生态观"
    ],
    "20260314100225": [
      "生物",
      "积累",
      "知识点::生物::生态系统::生态系统的组成成分",
      "题型::选择题::正误判断类",
      "知识点::生物::生态系统::生物群落的定义",
      "难度::基础::概念辨析类",
      "知识点::生物::生态系统::物种丰富度调查方法",
      "能力素养::生物::科学思维::概念辨析",
      "知识点::生物::生态系统::生物多样性的价值",
      "能力素养::生物::生命观念",
      "题型::选择题::单项选择题"
    ],
    "20260314100325": [
      "题型::图表信息题::表格数据分析",
      "知识点::生物::群落::物种丰富度",
      "能力素养::生物::科学思维::信息提取与分析",
      "知识点::生物::生态系统与环境保护::生物多样性及其价值",
      "难度::中档::多考点综合",
      "能力素养::生物::社会责任::生态环境保护认知",
      "能力素养::生物::生命观念::稳态与平衡观",
      "知识点::生物::生态系统与环境保护::生态系统的稳定性与自我调节",
      "知识点::生物::生态系统的结构::食物网",
      "题型::选择题::单项选择题"
    ],
    "20260314100633": [
      "生物",
      "积累",
      "知识点::生物::生态系统::稳定性::抵抗力稳定性",
      "知识点::生物::生态系统::物质循环",
      "题型::选择题::多项选择题::高考真题",
      "能力素养::生物::科学思维::逻辑推理判断",
      "难度::中档::多考点综合",
      "能力素养::生物::生命观念::稳态与平衡观",
      "知识点::生物::群落::群落的空间结构::垂直结构",
      "知识点::生物::生态系统::能量流动::流入生态系统的总能量"
    ],
    "20260314100743": [
      "生物",
      "积累",
      "思维",
      "能力素养::生物::社会责任::生态保护意识",
      "难度::中档::高考真题::多考点综合",
      "知识点::生物::稳态与环境::生态保护::生物多样性保护",
      "知识点::生物::稳态与环境::生态系统::能量流动::营养级能量去向",
      "知识点::生物::稳态与环境::群落::生态位::研究内容与意义",
      "题型::解答题::生态类综合题",
      "能力素养::生物::生命观念::稳态与平衡观",
      "能力素养::生物::科学思维::图表信息分析"
    ],
    "20260314100802": [
      "生物",
      "积累",
      "思维",
      "知识点::生物::稳态与环境::生态系统::负反馈调节",
      "知识点::生物::稳态与环境::生态系统::生态系统稳定性::抵抗力稳定性",
      "题型::解答题::生物简答题",
      "题型::高考真题::2023年::全国乙卷",
      "能力素养::生物::科学思维::逻辑推理",
      "能力素养::生物::科学探究::问题解释与表达",
      "知识点::生物::稳态与环境::生态系统::生态系统自我调节能力",
      "难度::中档::多个基础考点综合",
      "能力素养::生物::生命观念::稳态与平衡观",
      "知识点::生物::稳态与环境::生态系统::食物链与营养级"
    ],
    "20260314101445": [
      "生物",
      "积累",
      "思维",
      "能力素养::生物::社会责任::生态保护意识",
      "能力素养::生物::科学思维::图表信息分析",
      "题型::解答题::生物生态类综合题",
      "知识点::生物::稳态与环境::生态工程::生态学基本原理",
      "知识点::生物::稳态与环境::生态系统的物质循环::碳循环",
      "知识点::生物::稳态与环境::群落::生态位",
      "知识点::生物::细胞代谢::细胞呼吸::无氧呼吸",
      "知识点::生物::生态系统::湿地生态系统::蓝碳生态系统",
      "难度::中档::多考点综合",
      "能力素养::生物::生命观念::物质与能量观",
      "知识点::生物::稳态与环境::群落::群落演替"
    ],
    "20260314101518": [
      "生物",
      "积累",
      "思维",
      "题型::高考真题::湖北卷::2022年",
      "知识点::生物::生态系统::生态系统的组成成分",
      "知识点::生物::生态系统::物质循环的过程",
      "题型::非选择题::生态系统综合题",
      "知识点::生物::生态系统::能量流动的特点与传递效率",
      "能力素养::生物::社会责任::生产实践应用",
      "难度::中档::多考点综合",
      "知识点::生物::生态系统::能量流动的实践应用",
      "题型::非选择题::填空题",
      "能力素养::生物::生命观念::稳态与平衡观",
      "能力素养::生物::科学思维::模型分析",
      "难度::中档::高考真题类"
    ],
    "20260314101554": [
      "生物",
      "积累",
      "思维",
      "知识点::生物::种群::种群数量变化::S型增长与环境容纳量",
      "难度::中档::高考真题::多考点综合",
      "题型::解答题::生物实验分析题",
      "知识点::生物::生态系统::物质循环::碳循环",
      "知识点::生物::生态系统::能量流动",
      "知识点::生物::群落::群落特征与演替",
      "能力素养::生物::生命观念::稳态与平衡观",
      "能力素养::生物::科学思维::图表信息提取与分析",
      "能力素养::生物::科学探究::实验结果分析"
    ],
    "20260314103748": [
      "生物",
      "积累",
      "思维",
      "难度::中档::高考真题::多考点综合",
      "题型::解答题::生物非选择题::生态综合题",
      "知识点::生物::生态系统::物质循环::碳循环",
      "能力素养::生物::科学探究::实验结果分析",
      "知识点::生物::种群::种群数量变化::S型增长",
      "知识点::生物::群落::群落演替::次生演替",
      "知识点::生物::种群::种群数量变化::环境容纳量(K值)",
      "能力素养::生物::生命观念::物质与能量观",
      "知识点::生物::群落::群落的特征::物种组成",
      "能力素养::生物::科学思维::图表信息分析",
      "知识点::生物::生态系统::能量流动::能量流动过程分析"
    ],
    "20260314103811": [
      "生物",
      "积累",
      "思维",
      "题型::非选择题::填空题::生态系统综合考查",
      "知识点::生物::生物与环境::生态系统::能量流动::林德曼能量流动研究",
      "题型::高考真题::2021年::全国甲卷",
      "能力素养::生物::科学思维::理解应用",
      "知识点::生物::生物与环境::生态系统::能量流动::能量流动的特点",
      "知识点::生物::生物与环境::生态系统::种间关系::捕食的意义",
      "难度::基础::教材识记类",
      "能力素养::生物::生命观念::生态观"
    ],
    "20260314104007": [
      "生物",
      "积累",
      "能力素养::生物::社会责任::生态保护认知",
      "知识点::生物::生态系统::碳循环",
      "知识点::生物::生态系统::生产者与消费者功能",
      "能力素养::生物::科学思维::信息提取与分析",
      "难度::中档::概念辨析类",
      "题型::选择题::单项选择题::高考真题",
      "知识点::生物::生态环境保护::生态足迹",
      "知识点::生物::生态环境保护::碳中和"
    ],
    "20260314104020": [
      "生物",
      "积累",
      "难度::容易::概念判断类",
      "知识点::化学::化学与STSE::环境保护::碳达峰碳中和",
      "题型::选择题::单项选择题::高考选考真题",
      "知识点::化学::化学与能源资源开发利用",
      "能力素养::化学::科学态度与社会责任::生态环境保护意识"
    ],
    "20260314104036": [
      "生物",
      "积累",
      "能力素养::生物::社会责任::生态保护意识",
      "知识点::生物::生物与环境::生物与环境的相互关系",
      "难度::基础::概念辨析类",
      "知识点::生物::生态保护::可持续发展理念",
      "题型::选择题::单项选择题"
    ],
    "20260314104048": [
      "生物",
      "积累",
      "题型::选择题::高考真题::2022湖北卷",
      "能力素养::生物::社会责任::生态保护意识考查",
      "知识点::生物::稳态与环境::生物多样性的保护措施",
      "能力素养::生物::科学思维::信息提取与正误判断",
      "知识点::生物::生态保护::就地保护与易地保护辨析",
      "知识点::生物::生态修复::长江禁渔政策相关考点",
      "难度::基础::概念理解辨析类",
      "题型::选择题::单项选择题"
    ],
    "20260314104100": [
      "生物",
      "积累",
      "知识点::生物::生态农业::常见生态农业模式",
      "知识点::生物::可持续发展::生态保护实践措施",
      "能力素养::生物::社会责任::生态环境保护意识",
      "能力素养::生物::科学思维::实例分析与判断",
      "难度::基础::概念辨析类",
      "题型::选择题::高考真题",
      "知识点::生物::生态与环境::生态足迹::减少生态足迹的措施",
      "题型::选择题::单项选择题"
    ],
    "20260314104111": [
      "生物",
      "积累",
      "能力素养::生物::社会责任::生态保护认知",
      "题型::选择题::时政情境类",
      "能力素养::生物::科学思维::概念区分",
      "知识点::生物::生物与环境::生物多样性的价值::直接价值",
      "难度::基础::概念辨析类",
      "知识点::生物::生物与环境::生物多样性的价值",
      "知识点::生物::生物与环境::生物多样性的价值::间接价值",
      "题型::选择题::单项选择题"
    ],
    "20260314104123": [
      "生物",
      "积累",
      "知识点::生物::生态与环境保护::生物多样性保护::易地保护",
      "能力素养::生物::科学思维::概念辨析应用",
      "难度::基础::概念辨析类",
      "能力素养::生物::生命观念::生态保护认知",
      "题型::选择题::单项选择题::正误判断类"
    ],
    "20260314104304": [
      "生物",
      "积累",
      "能力素养::生物::生命观念::结构与功能观",
      "知识点::生物::生物与环境::种群::种群密度调查方法::样线法",
      "题型::选择题::正误判断类",
      "知识点::生物::生物与环境::生物多样性::易地保护",
      "能力素养::生物::科学探究::调查方法实践应用",
      "难度::基础::概念辨析类",
      "知识点::生物::生物与环境::生态系统::栖息地对物种分布的影响",
      "能力素养::生物::科学思维::图表信息提取与分析",
      "知识点::生物::生物与环境::生物多样性::物种多样性调查",
      "知识点::生物::生物与环境::群落::群落结构",
      "题型::高考真题::辽宁卷::2022年",
      "题型::选择题::单项选择题"
    ],
    "20260314104357": [
      "生物",
      "积累",
      "知识点::生物::生物与环境::生物多样性的层次判断",
      "难度::基础::概念辨析类",
      "能力素养::生物::科学思维::概念辨析",
      "题型::选择题::高考真题",
      "能力素养::生物::生命观念",
      "题型::选择题::单项选择题"
    ],
    "20260314104415": [
      "生物",
      "积累",
      "知识点::生物::生态系统::生态系统的稳定性::抵抗力稳定性",
      "能力素养::生物::生命观念::结构与功能观",
      "知识点::生物::群落::群落的空间结构",
      "难度::中档::易混淆群落垂直与水平结构",
      "知识点::生物::生态工程::协调与平衡原理",
      "知识点::生物::生物与环境::生物对环境的适应性",
      "题型::高考真题::辽宁卷",
      "能力素养::生物::科学思维::信息提取与辨析",
      "题型::选择题::单项选择题"
    ],
    "20260314105603": [
      "生物",
      "积累",
      "知识点::生物::选择性必修二::生态系统及其稳定性::抵抗力稳定性",
      "难度::基础::概念辨析类",
      "题型::高考真题::2023湖南卷",
      "能力素养::生物::生命观念::稳态与平衡观",
      "题型::选择题::不定项选择题",
      "知识点::生物::选择性必修二::生态环境保护::生态足迹与生态承载力",
      "知识点::生物::选择性必修二::生态工程::基本原理::自生原理",
      "知识点::生物::选择性必修二::生态工程::基本原理::整体性原理",
      "能力素养::生物::社会责任::生态文明建设认知"
    ],
    "20260314105627": [
      "生物",
      "积累",
      "能力素养::生物::社会责任::生态保护意识",
      "知识点::生物::生态与环境::生物多样性及其保护",
      "知识点::生物::生态与环境::可持续发展理念",
      "题型::选择题::正误判断类",
      "知识点::生物::生态与环境::生态系统破碎化的影响",
      "难度::基础::概念辨析类",
      "题型::选择题::不定项选择题",
      "能力素养::生物::生命观念::生态观"
    ],
    "20260314105726": [
      "生物",
      "积累",
      "思维",
      "能力素养::生物::社会责任::生态保护意识",
      "知识点::生物::生态保护::气候变化对生境的影响",
      "能力素养::生物::科学思维::信息提取与整合能力",
      "知识点::生物::生物多样性::生物多样性的意义",
      "知识点::生物::种群::种群生存风险分析",
      "知识点::生物::生物多样性::生物多样性保护措施",
      "知识点::生物::生态系统::食物链书写",
      "题型::高考真题::2023年::湖北卷",
      "难度::中档::需结合材料提取信息作答",
      "题型::非选择题::材料分析题"
    ],
    "20260314105907": [
      "生物",
      "积累",
      "思维",
      "知识点::生物::生态系统::碳循环",
      "能力素养::生物::社会责任::生态保护应用",
      "知识点::生物::种群::环境容纳量",
      "知识点::生物::生态系统::组成成分::生产者",
      "知识点::生物::种群::种群密度变化分析",
      "难度::中档::多个生态考点综合",
      "知识点::生物::群落::空间结构::水平结构",
      "题型::非选择题::生态综合解答题",
      "能力素养::生物::科学思维::图表信息提取与分析",
      "知识点::生物::生物多样性::生物多样性的价值",
      "知识点::生物::生态系统::稳定性",
      "能力素养::生物::生命观念::生态观"
    ],
    "20260314110004": [
      "生物",
      "积累",
      "思维",
      "知识点::生物::种群与群落::种群数量特征",
      "难度::中档::高考真题::多考点综合",
      "知识点::生物::生态系统及其稳定性::负反馈调节机制",
      "能力素养::生物::科学思维::信息提取与分析",
      "知识点::生物::生态系统及其稳定性::自我调节能力",
      "知识点::生物::种群与群落::种群数量变化影响因素",
      "能力素养::生物::生命观念::稳态与平衡观",
      "知识点::生物::生物多样性::生物多样性的价值",
      "题型::解答题::表格信息分析题"
    ],
    "20260314110023": [
      "生物",
      "积累",
      "思维",
      "能力素养::生物::社会责任::生态保护意识",
      "知识点::生物::稳态与环境::生态系统::生态系统的稳定性",
      "题型::非选择题::生态综合类",
      "题型::非选择题::多选类",
      "知识点::生物::稳态与环境::生态系统::食物链与食物网::营养级判断",
      "知识点::生物::稳态与环境::生态系统::人类活动对生态系统的影响",
      "难度::中档::多考点综合应用",
      "题型::非选择题::填空类",
      "能力素养::生物::生命观念::稳态与平衡观",
      "知识点::生物::稳态与环境::生态系统::能量流动::能量流动的特点",
      "能力素养::生物::科学思维::信息提取与逻辑推理"
    ],
    "20260314111811": [
      "生物",
      "积累",
      "知识点::生物::生物多样性::保护措施",
      "能力素养::生物::社会责任::生态保护意识",
      "知识点::生物::生物多样性::价值",
      "知识点::生物::生物多样性::内涵",
      "难度::基础::概念辨析类",
      "能力素养::生物::科学思维::概念辨析",
      "题型::选择题::单项选择题::正误判断类",
      "能力素养::生物::生命观念::生态观"
    ],
    "20260314111821": [
      "生物",
      "积累",
      "能力素养::生物::生命观念::结构与功能观",
      "知识点::生物::生态系统::食物链与食物网",
      "知识点::生物::生态系统::生态系统的结构::营养级",
      "难度::基础::概念辨析类",
      "题型::选择题::概念辨析类选择题",
      "能力素养::生物::科学思维::概念辨析",
      "知识点::生物::种群::种群数量变化的影响因素",
      "知识点::生物::生物的进化::生殖隔离",
      "题型::选择题::单项选择题"
    ],
    "20260314111836": [
      "生物",
      "积累",
      "知识点::生物::选择性必修2::生物与环境::生态工程的自生原理",
      "知识点::生物::选择性必修2::生物与环境::生态系统的稳定性",
      "题型::选择题::正误判断类",
      "难度::基础::概念辨析类",
      "能力素养::生物::生命观念::稳态与平衡观",
      "能力素养::生物::科学思维::概念辨析",
      "知识点::生物::选择性必修2::生物与环境::生态平衡的维持",
      "题型::选择题::单项选择题"
    ],
    "20260314111848": [
      "生物",
      "积累",
      "题型::选择题::单项选择题::高考模拟题",
      "知识点::生物::生态系统的功能::信息传递::信息类型",
      "知识点::生物::生物多样性及其保护::保护措施",
      "难度::基础::概念辨析类",
      "能力素养::生物::生命观念",
      "能力素养::生物::科学思维::概念判断",
      "知识点::生物::生物多样性及其保护::生物多样性的价值",
      "知识点::生物::群落::群落的结构::水平结构"
    ],
    "20260314111900": [
      "生物",
      "积累",
      "能力素养::生物::科学思维::概念理解",
      "知识点::生物::生态系统::物质循环::碳循环",
      "知识点::生物::生态环境::碳中和",
      "题型::选择题::单项选择题::正误判断题",
      "难度::基础::概念辨析类",
      "能力素养::生物::生命观念::稳态与平衡观"
    ],
    "20260314111924": [
      "生物",
      "积累",
      "知识点::生物::选择性必修2::生态系统::生态系统稳定性",
      "能力素养::生物::科学思维::信息分析判断",
      "知识点::生物::选择性必修2::生态系统::生态农业",
      "难度::基础::概念辨析类",
      "知识点::生物::选择性必修2::生态系统::能量流动",
      "知识点::生物::选择性必修2::生态系统::物质循环",
      "能力素养::生物::生命观念",
      "题型::选择题::单项选择题"
    ],
    "20260314112019": [
      "生物",
      "积累",
      "题型::选择题::单项选择题::正误判断类",
      "能力素养::生物::生命观念::物质能量观",
      "知识点::生物::生态工程::生态农业设计",
      "知识点::生物::实验探究::对照实验结果分析",
      "能力素养::生物::科学思维::图表数据分析",
      "难度::中档::图表信息提取类",
      "能力素养::生物::科学探究::对照实验设计分析",
      "题型::选择题::单项选择题::情境综合类",
      "知识点::生物::稳态与环境::生态系统功能::物质循环",
      "知识点::生物::稳态与环境::生态系统功能::能量流动"
    ],
    "20260314112052": [
      "生物",
      "积累",
      "知识点::生物::生物多样性::价值",
      "知识点::生物::生态系统::微生物分解作用",
      "知识点::生物::生态工程::生态修复",
      "知识点::生物::生态系统::能量流动",
      "能力素养::生物::科学思维::信息提取与分析",
      "知识点::生物::生态系统::种间关系",
      "知识点::生物::生态环境治理::水体富营养化治理",
      "难度::基础::概念辨析类",
      "能力素养::生物::社会责任::生态环境保护意识",
      "能力素养::生物::生命观念::稳态与平衡观",
      "题型::选择题::单项选择题::选非题"
    ],
    "20260314112129": [
      "生物",
      "积累",
      "知识点::生物::稳态与环境::生态系统::生态承载力与生态盈余",
      "能力素养::生物::社会责任::生态保护意识",
      "题型::生物::表格数据分析类习题",
      "能力素养::生物::科学思维::信息提取与逻辑判断",
      "难度::中档::图表数据结合考点考查",
      "知识点::生物::稳态与环境::生态工程::生态工程基本原理",
      "能力素养::生物::生命观念::生态平衡观念",
      "知识点::生物::稳态与环境::生态系统::生态足迹概念",
      "题型::选择题::单项选择题"
    ],
    "20260314112155": [
      "生物",
      "积累",
      "题型::选择题::正误判断类",
      "题型::选择题::图表分析类",
      "难度::中档::多考点综合",
      "知识点::生物::生态系统::能量流动::能量传递效率计算",
      "能力素养::生物::生命观念::稳态与平衡观",
      "知识点::生物::生态系统::能量流动::同化量计算",
      "题型::选择题::单项选择题",
      "能力素养::生物::科学思维::数据计算与分析",
      "知识点::生物::生态系统的稳定性::抵抗力稳定性",
      "知识点::生物::生态系统::能量流动::能量流动的去路"
    ],
    "20260314112232": [
      "生物",
      "积累",
      "思维",
      "知识点::生物::生态系统::碳循环",
      "知识点::生物::生态系统::物质循环与能量流动的关系",
      "题型::选择题::多项选择题",
      "知识点::生物::生态系统::能量流动",
      "难度::中档::图表信息提取",
      "难度::中档::多考点综合",
      "题型::选择题::图表分析类",
      "能力素养::生物::生命观念::物质与能量观",
      "能力素养::生物::科学思维::模型分析"
    ],
    "20260314112342": [
      "生物",
      "积累",
      "难度::中档::多考点综合::易混概念辨析",
      "题型::模考题::地方二模::辽宁沈阳二模",
      "知识点::生物::生物与环境::种间关系::互利共生与寄生辨析",
      "能力素养::生物::生命观念::进化与适应观",
      "知识点::生物::生态系统::生态系统结构::营养级判定",
      "知识点::生物::生态系统::生态系统功能::能量流动规律",
      "知识点::生物::生物进化::协同进化",
      "题型::选择题::不定项选择题",
      "能力素养::生物::科学思维::逻辑推理"
    ],
    "20260314112354": [
      "生物",
      "积累",
      "题型::选择题::多项选择题",
      "知识点::生物::选择性必修二::生物与环境::生态系统的组成成分",
      "能力素养::生物::科学思维::概念辨析",
      "难度::中档::易混概念辨析",
      "知识点::生物::选择性必修二::生物与环境::生态系统的结构",
      "知识点::生物::选择性必修二::生物与环境::生物多样性的价值",
      "能力素养::生物::生命观念::生态观"
    ],
    "20260314112425": [
      "生物",
      "积累",
      "知识点::生物::生物与环境::全球性生态环境问题::水华治理",
      "题型::选择题::不定项选择题::表格信息类",
      "难度::中档::易混概念辨析+实验数据综合",
      "知识点::生物::生物与环境::生态系统的稳定性",
      "知识点::生物::生物与环境::生物多样性的价值",
      "知识点::生物::实验与探究::实验结果数据分析",
      "能力素养::生物::生命观念::稳态与平衡观",
      "能力素养::生物::科学思维::信息获取与分析判断",
      "知识点::生物::生物与环境::生态工程的基本原理"
    ],
    "20260314112525": [
      "生物",
      "积累",
      "思维",
      "知识点::生物::生物与环境::种间关系",
      "难度::中档::多考点综合::含图表分析",
      "知识点::生物::生物与环境::生物入侵",
      "知识点::生物::生物与环境::生态系统的稳定性",
      "知识点::生物::生物与环境::生态修复::水体富营养化治理",
      "能力素养::生物::生命观念::稳态与平衡观",
      "知识点::生物::生物与环境::种群特征::年龄结构",
      "能力素养::生物::科学思维::图表信息提取与分析",
      "知识点::生物::生物与环境::物质循环::N、P元素循环",
      "题型::解答题::生物::生态类综合题",
      "能力素养::生物::社会责任::生态环境保护应用"
    ],
    "20260314112541": [
      "生物",
      "积累",
      "思维",
      "知识点::生物::选择性必修二::生物与环境::种间关系",
      "知识点::生物::选择性必修一::植物生命活动调节::光敏色素的作用",
      "难度::中档::多考点综合考查",
      "能力素养::生物::科学思维::归纳与概括",
      "能力素养::生物::社会责任::有害生物防治应用",
      "能力素养::生物::生命观念::稳态与平衡观",
      "知识点::生物::选择性必修二::生态系统及其稳定性::生态系统信息传递的类型",
      "题型::非选择题::填空题::生态系统综合题",
      "知识点::生物::选择性必修二::生态系统及其稳定性::生物防治",
      "知识点::生物::选择性必修二::生态系统及其稳定性::生态系统信息传递的功能"
    ],
    "20260314112607": [
      "生物",
      "积累",
      "思维",
      "题型::解答题::生态学综合题",
      "能力素养::生物::科学探究::实验结论阐释",
      "知识点::生物::实验探究::生态学实验::结果分析",
      "知识点::生物::群落::群落演替::次生演替",
      "难度::中档::多考点综合",
      "能力素养::生物::科学思维::信息提取与应用",
      "能力素养::生物::生命观念::稳态与平衡观",
      "题型::解答题::图表信息分析题",
      "知识点::生物::生态系统::能量流动::能量流动的去向",
      "知识点::生物::生态系统::能量流动::能量流动的意义",
      "知识点::生物::生态系统::生态系统合理利用"
    ],
    "20260314112653": [
      "生物",
      "积累",
      "思维",
      "题型::解答题::生物生态综合题",
      "知识点::生物::生态系统::生态系统的组成成分",
      "知识点::生物::生态系统::种间关系::生态位",
      "知识点::生物::生态系统::种间互作实验分析",
      "知识点::生物::生态系统::能量流动::生产者能量去向",
      "题型::实验题::图表信息分析题",
      "能力素养::生物::生命观念::稳态与平衡观",
      "能力素养::生物::科学思维::信息提取与逻辑推理",
      "难度::中档::多考点综合::图表分析",
      "能力素养::生物::科学探究::实验结果分析与预测"
    ],
    "20260314112727": [
      "生物",
      "积累",
      "思维",
      "知识点::生物::生态工程::协调原理",
      "知识点::生物::种群::种群数量计算",
      "知识点::生物::种群::种群密度调查::样方法",
      "知识点::生物::群落::群落结构::空间结构",
      "题型::解答题::生物填空题::图表信息分析",
      "难度::中档::多考点综合",
      "能力素养::生物::科学思维::信息提取与应用",
      "能力素养::生物::生命观念::稳态与平衡观",
      "知识点::生物::生态系统::生态系统的稳定性",
      "知识点::生物::群落::种间关系",
      "能力素养::生物::科学思维::逻辑推理",
      "知识点::生物::生态系统::生态系统结构::食物链与食物网"
    ],
    "20260314132239": [
      "语文",
      "难度::中档::多考点综合考查",
      "知识点::语文::现代文阅读::非连续性文本阅读::观点比较探究",
      "知识点::语文::现代文阅读::非连续性文本阅读::论证思路与手法分析",
      "能力素养::语文::思维发展与提升",
      "能力素养::语文::信息筛选与整合能力",
      "题型::简答题::词句作用分析",
      "知识点::语文::现代文阅读::非连续性文本阅读::内容理解与分析",
      "题型::现代文阅读题::非连续性文本阅读",
      "能力素养::语文::逻辑推理与论证分析能力",
      "知识点::语文::现代文阅读::非连续性文本阅读::词句表达效果赏析",
      "题型::简答题::跨材料观点对比探究",
      "能力素养::语文::语言建构与运用",
      "题型::选择题::单项选择题"
    ],
    "20260314133246": [
      "语文",
      "能力素养::语文::信息筛选与整合",
      "难度::中档::多文本综合考查",
      "知识点::语文::现代文阅读::论述类文本::内容理解分析",
      "题型::简答题::文本信息整合分析",
      "知识点::语文::文化传承::中华优秀传统文化的创造性转化与创新性发展",
      "能力素养::语文::文化传承与理解::传统文化当代价值阐释",
      "能力素养::语文::逻辑推理与判断",
      "知识点::语文::现代文阅读::论述类文本::开放探究",
      "知识点::语文::现代文阅读::论述类文本::观点正误判断",
      "知识点::语文::现代文阅读::论述类文本::论据匹配",
      "题型::现代文阅读::非连续性多文本阅读",
      "题型::选择题::单项选择题"
    ],
    "20260314134444": [
      "语文",
      "知识点::语文::现代文阅读::论述类文本::文本探究应用",
      "难度::中档::多考点综合考查",
      "能力素养::语文::逻辑推理与分析能力",
      "题型::阅读题::论述类文本阅读",
      "能力素养::语文::思维发展与提升",
      "能力素养::语文::信息筛选与整合能力",
      "知识点::语文::现代文阅读::论述类文本::内容理解与分析",
      "题型::简答题::论证思路分析",
      "知识点::语文::现代文阅读::论述类文本::核心观点概括",
      "题型::简答题::开放探究题",
      "知识点::语文::现代文阅读::论述类文本::论证结构分析",
      "题型::选择题::单项选择题"
    ],
    "20260314135624": [
      "语文",
      "知识点::语文::现代文阅读::现当代散文::内容要点概括",
      "题型::现代文阅读题::散文阅读::单项选择题",
      "难度::中档::主客观题型综合考查",
      "知识点::语文::现代文阅读::现当代散文::文学短评写作",
      "题型::现代文阅读题::散文阅读::探究类主观题",
      "能力素养::语文::思维发展与提升",
      "知识点::语文::现代文阅读::现当代散文::文本内容理解",
      "题型::现代文阅读题::散文阅读::内容概括主观题",
      "能力素养::语文::审美鉴赏与创造",
      "能力素养::语文::语言表达与运用能力",
      "知识点::语文::现代文阅读::现当代散文::句子鉴赏分析",
      "能力素养::语文::文本理解与分析能力"
    ],
    "20260314135902": [
      "语文",
      "知识点::语文::现代文阅读::主旨意蕴探究",
      "知识点::语文::现代文阅读::内容理解分析",
      "题型::解答题::现代文阅读::简答题",
      "能力素养::语文::思维发展与提升",
      "能力素养::语文::文化传承与理解",
      "难度::中档::多考点综合",
      "能力素养::语文::审美鉴赏与创造",
      "知识点::语文::现代文阅读::艺术特色鉴赏",
      "知识点::语文::作家作品::沈从文",
      "知识点::语文::现代文阅读::表达技巧分析",
      "知识点::语文::现代文阅读::文学类文本阅读::小说阅读",
      "题型::选择题::单项选择题"
    ],
    "20260314140046": [
      "语文",
      "知识点::语文::现代文阅读::散文::内容理解",
      "知识点::语文::现代文阅读::散文::艺术特色鉴赏",
      "能力素养::语文::信息筛选与整合",
      "难度::中档::多题型多考点综合",
      "题型::现代文阅读::散文阅读",
      "知识点::语文::现代文阅读::散文::细节描写赏析",
      "能力素养::语文::思维发展与提升::文本分析",
      "知识点::语文::现代文阅读::散文::《到橘子林去》",
      "知识点::语文::现代文阅读::散文::标题作用分析",
      "题型::主观题::文本探究题",
      "能力素养::语文::审美鉴赏与创造",
      "题型::选择题::单项选择题"
    ],
    "20260314140218": [
      "语文",
      "知识点::语文::现代文阅读::散文::艺术特色鉴赏",
      "知识点::语文::现代文阅读::多文本联动探究",
      "知识点::语文::现代文阅读::散文::语言表达效果赏析",
      "知识点::语文::现代文阅读::散文::内容理解分析",
      "能力素养::语文::思维发展与提升",
      "题型::解答题::现代文阅读主观题::观点探究",
      "难度::中档::多考点综合",
      "能力素养::语文::审美鉴赏与创造",
      "题型::解答题::现代文阅读主观题::语言效果分析",
      "能力素养::语文::语言建构与运用",
      "题型::选择题::单项选择题"
    ],
    "20260314140534": [
      "语文",
      "能力素养::语文::文化传承与理解::劳动价值认知",
      "题型::解答题::简答题::物象关联分析",
      "题型::解答题::简答题::结尾段落作用分析",
      "难度::中档::多考点综合",
      "知识点::语文::现代文阅读::散文阅读::内容与艺术特色鉴赏",
      "题型::选择题::单项选择题::文本赏析正误判断",
      "能力素养::语文::审美鉴赏与创造",
      "知识点::语文::现代文阅读::散文阅读::段落作用分析",
      "能力素养::语文::思维发展与提升::文本逻辑分析",
      "能力素养::语文::语言建构与运用::文本内容理解",
      "知识点::语文::现代文阅读::散文阅读::物象内在联系分析"
    ],
    "20260314140709": [
      "语文",
      "难度::中档::多考点综合考查",
      "题型::现代文阅读题::简答题::内容探究类",
      "能力素养::语文::思维发展与提升",
      "知识点::语文::现代文阅读::句段作用分析",
      "知识点::语文::现代文阅读::情感意蕴探究",
      "知识点::语文::现代文阅读::散文::书信体散文阅读",
      "知识点::语文::现代文阅读::内容理解与分析",
      "能力素养::语文::审美鉴赏与创造",
      "知识点::语文::现代文阅读::艺术特色鉴赏",
      "知识点::语文::现代文阅读::人物情感变化分析",
      "题型::现代文阅读题::简答题::情感分析类",
      "能力素养::语文::文本解读能力",
      "题型::现代文阅读题::单项选择题"
    ],
    "20260314140900": [
      "语文",
      "难度::中档::多考点综合考查",
      "知识点::语文::现代文阅读::散文::内容与艺术特色鉴赏",
      "题型::简答题::文本分析类",
      "能力素养::语文::审美鉴赏与创造",
      "题型::选择题::单项选择题",
      "能力素养::语文::思维发展与提升::文本解读能力",
      "知识点::语文::现代文阅读::散文::关键语句作用分析",
      "知识点::语文::现代文阅读::散文::文意理解与原因概括",
      "题型::现代文阅读题::散文阅读"
    ],
    "20260314141159": [
      "语文",
      "知识点::语文::现代文阅读::散文阅读::行文线索分析",
      "知识点::语文::现代文阅读::散文阅读::内容理解",
      "题型::现代文阅读题::简答题::线索分析",
      "知识点::语文::现代文阅读::散文阅读::艺术特色鉴赏",
      "难度::中档::多考点综合",
      "能力素养::语文::审美鉴赏与创造",
      "知识点::语文::现代文阅读::散文阅读::描写作用分析",
      "题型::现代文阅读题::简答题::作用分析",
      "题型::现代文阅读题::散文阅读",
      "能力素养::语文::思维发展与提升::文本解读能力",
      "题型::现代文阅读题::单项选择题"
    ],
    "20260314141514": [
      "语文",
      "难度::中档::多考点综合考查",
      "能力素养::语文::积累::文学鉴赏经验运用",
      "知识点::语文::现代文阅读::散文阅读::内容与艺术特色分析鉴赏",
      "能力素养::语文::审美鉴赏与创造::散文意象把握",
      "题型::现代文阅读题::散文阅读::行文思路分析题",
      "知识点::语文::现代文阅读::散文阅读::标题作用::全文统摄作用分析",
      "题型::现代文阅读题::散文阅读::内容赏析题",
      "题型::现代文阅读题::散文阅读::标题作用分析题",
      "知识点::语文::现代文阅读::散文阅读::叙述层次分析",
      "能力素养::语文::思维::文本逻辑梳理能力",
      "能力素养::语文::文化传承与理解::红色文化认知",
      "题型::现代文阅读题::散文阅读::简答题",
      "题型::选择题::单项选择题"
    ],
    "20260314143850": [
      "数学",
      "积累",
      "测试1::测试2",
      "知识点::数学::解三角形::正弦定理",
      "知识点::数学::解三角形::余弦定理",
      "能力素养::数学::逻辑推理",
      "知识点::数学::解三角形::内角计算",
      "能力素养::数学::数学运算",
      "难度::容易::公式直接应用",
      "题型::选择题::单项选择题",
      "打印::数学::原三角函数"
    ],
    "20260321124605": [
      "数学",
      "思维",
      "题型::填空题::高考真题",
      "知识点::数学::解三角形::余弦定理的应用",
      "能力素养::数学::逻辑推理",
      "知识点::数学::解三角形::夹角余弦值计算",
      "难度::中档::多步运算",
      "能力素养::数学::运算求解",
      "打印::数学::原三角函数"
    ],
    "20260321124704": [
      "数学",
      "思维",
      "题型::填空题::高考真题::解三角形计算",
      "知识点::数学::解三角形::三角形内角和定理",
      "知识点::数学::解三角形::正弦定理",
      "能力素养::数学::逻辑推理",
      "难度::基础::多考点综合应用",
      "知识点::数学::三角函数::同角三角函数基本关系",
      "能力素养::数学::数学运算",
      "打印::数学::原三角函数"
    ],
    "20260321124805": [
      "数学",
      "思维",
      "题型::填空题::高考真题",
      "题型::填空题",
      "难度::中档::公式综合应用",
      "知识点::数学::解三角形::正弦定理",
      "能力素养::数学::逻辑推理",
      "知识点::数学::三角函数::同角三角函数基本关系",
      "能力素养::数学::运算求解",
      "知识点::数学::三角形内角性质",
      "打印::数学::原三角函数"
    ],
    "20260321124856": [
      "数学",
      "思维",
      "题型::填空题::高考真题",
      "难度::基础::公式直接应用",
      "知识点::数学::解三角形::三角形内角和定理",
      "知识点::数学::解三角形::正弦定理",
      "能力素养::数学::逻辑推理",
      "题型::填空题::解三角形计算",
      "能力素养::数学::数学运算",
      "知识点::数学::解三角形::已知两边及一对角求未知角",
      "打印::数学::原三角函数"
    ],
    "20260321124923": [
      "数学",
      "思维",
      "题型::填空题::高考真题::解三角形求值",
      "知识点::数学::必修第五册::解三角形::余弦定理",
      "能力素养::数学::逻辑推理",
      "知识点::数学::必修第五册::解三角形::正弦定理",
      "知识点::数学::解三角形::边角互化",
      "难度::基础::单一考点应用",
      "能力素养::数学::数学运算",
      "打印::数学::原三角函数"
    ],
    "20260321125033": [
      "数学",
      "思维",
      "难度::基础::公式直接应用",
      "知识点::数学::解三角形::三角形内角和定理",
      "知识点::数学::解三角形::正弦定理",
      "能力素养::数学::运算求解能力",
      "题型::填空题::高考真题::计算类",
      "知识点::数学::解三角形::边角互化",
      "能力素养::数学::逻辑推理能力",
      "打印::数学::原三角函数"
    ],
    "20260321125111": [
      "数学",
      "思维",
      "题型::填空题::高考真题",
      "难度::基础::双考点综合",
      "知识点::数学::必修五::解三角形::三角形面积公式",
      "能力素养::数学::逻辑推理",
      "能力素养::数学::数学运算",
      "知识点::数学::必修五::解三角形::余弦定理",
      "打印::数学::原三角函数"
    ],
    "20260321125413": [
      "数学",
      "思维",
      "难度::基础::公式直接应用",
      "题型::填空题",
      "知识点::数学::解三角形::正弦定理",
      "能力素养::数学::运算求解能力",
      "知识点::数学::三角形内角和定理",
      "打印::数学::原三角函数"
    ],
    "20260321125444": [
      "数学",
      "思维",
      "知识点::数学::必修五::解三角形::正弦定理",
      "题型::填空题::高考真题",
      "知识点::数学::三角形::内角和定理",
      "题型::填空题::文科数学",
      "能力素养::数学::逻辑推理",
      "知识点::数学::三角函数::特殊角的三角函数值计算",
      "能力素养::数学::数学运算",
      "难度::基础::单考点应用",
      "打印::数学::原三角函数"
    ],
    "20260321125527": [
      "数学",
      "思维",
      "题型::填空题::高考真题",
      "难度::基础::公式直接应用",
      "知识点::数学::解三角形::正弦定理",
      "知识点::数学::解三角形::余弦定理",
      "能力素养::数学::逻辑推理",
      "知识点::数学::解三角形::边角互化",
      "能力素养::数学::运算求解",
      "打印::数学::原三角函数"
    ],
    "20260321125704": [
      "数学",
      "思维",
      "知识点::数学::解三角形::三角形面积公式",
      "知识点::数学::解三角形::余弦定理",
      "能力素养::数学::逻辑推理",
      "能力素养::数学::数学运算",
      "知识点::数学::解三角形::同角三角函数基本关系",
      "难度::中档::高考真题类",
      "题型::解答题::解三角形综合应用",
      "打印::数学::原三角函数"
    ],
    "20260321130103": [
      "数学",
      "思维",
      "题型::解答题::解三角形::综合计算",
      "知识点::数学::解三角形::正弦定理",
      "知识点::数学::解三角形::余弦定理",
      "能力素养::数学::逻辑推理",
      "难度::中档::高考常规考点综合",
      "知识点::数学::解三角形::三角形面积计算",
      "知识点::数学::三角恒等变换::正弦和差角公式",
      "能力素养::数学::运算求解",
      "打印::数学::原三角函数"
    ],
    "20260321130200": [
      "数学",
      "思维",
      "知识点::数学::解三角形::三角形面积公式",
      "知识点::数学::解三角形::正弦定理",
      "知识点::数学::解三角形::余弦定理",
      "能力素养::数学::逻辑推理",
      "难度::中档::高考真题::双小问综合",
      "题型::解答题::解三角形::高考真题",
      "知识点::数学::三角恒等变换::两角和的正弦公式",
      "能力素养::数学::数学运算",
      "知识点::数学::解三角形::同角三角函数基本关系",
      "打印::数学::原三角函数"
    ],
    "20260321130449": [
      "数学",
      "思维",
      "题型::解答题::证明+计算双设问",
      "知识点::数学::解三角形::正弦定理",
      "知识点::数学::解三角形::余弦定理",
      "能力素养::数学::逻辑推理",
      "难度::中档::隐含三角形构成条件验证陷阱",
      "难度::中档::多考点综合",
      "知识点::数学::解三角形::边角互化",
      "能力素养::数学::思维",
      "题型::解答题::解三角形类",
      "知识点::数学::解三角形::三角形三边关系",
      "能力素养::数学::数学运算",
      "打印::数学::原三角函数"
    ],
    "20260321130626": [
      "数学",
      "思维",
      "知识点::数学::解三角形::三角形面积公式",
      "知识点::数学::解三角形::余弦定理",
      "能力素养::数学::逻辑推理",
      "知识点::数学::三角函数::二倍角正弦公式",
      "难度::基础::多知识点综合应用",
      "题型::解答题::解三角形综合题",
      "知识点::数学::解三角形::三角形周长计算",
      "能力素养::数学::数学运算",
      "打印::数学::原三角函数"
    ],
    "20260321130710": [
      "数学",
      "思维",
      "能力素养::数学::逻辑推理",
      "能力素养::数学::信息提取与应用",
      "题型::选择题::单项选择题::高考真题",
      "知识点::数学::平面几何::圆的基本性质",
      "难度::中档::多考点综合",
      "知识点::数学::数学文化::中国古代数学算法应用",
      "知识点::数学::解三角形::等边三角形边长计算",
      "能力素养::数学::数学运算",
      "知识点::数学::代数运算::公式代入求值",
      "打印::数学::原三角函数"
    ],
    "20260321130932": [
      "数学",
      "思维",
      "知识点::数学::平面几何::面积计算::扇形面积计算",
      "知识点::数学::最值问题::几何动态最值求解",
      "题型::选择题::单项选择题::高考文科真题",
      "知识点::数学::平面几何::圆::圆周角性质",
      "能力素养::数学::逻辑推理",
      "能力素养::数学::直观想象",
      "难度::中档::多知识点综合",
      "知识点::数学::平面几何::面积计算::三角形面积计算",
      "能力素养::数学::数学运算",
      "打印::数学::原三角函数"
    ],
    "20260321131336": [
      "数学",
      "思维",
      "能力素养::数学::逻辑推理",
      "难度::中档::2个考点综合",
      "知识点::数学::三角恒等变换::半角公式",
      "知识点::数学::三角函数::象限角与三角函数符号判断",
      "能力素养::数学::运算求解",
      "题型::选择题::单项选择题",
      "打印::数学::原三角函数"
    ],
    "20260321131703": [
      "数学",
      "思维",
      "知识点::数学::三角函数::两角和与差的正弦公式",
      "难度::中档::公式综合应用",
      "能力素养::数学::逻辑推理",
      "能力素养::数学::数学运算",
      "知识点::数学::三角函数::二倍角的余弦公式",
      "题型::选择题::单项选择题",
      "打印::数学::原三角函数"
    ],
    "20260321131735": [
      "数学",
      "思维",
      "知识点::数学::三角函数::特殊角三角函数求值",
      "难度::基础::简单运算类",
      "题型::选择题::单项选择题::高考真题",
      "能力素养::数学::数学运算",
      "知识点::数学::三角函数::二倍角公式",
      "打印::数学::原三角函数"
    ],
    "20260321131858": [
      "数学",
      "思维",
      "知识点::数学::三角函数::三角恒等变换::二倍角公式",
      "能力素养::数学::逻辑推理",
      "题型::选择题::单项选择题::高考真题",
      "难度::中档::多公式综合运算",
      "知识点::数学::三角函数::同角三角函数基本关系",
      "能力素养::数学::运算求解",
      "打印::数学::原三角函数"
    ],
    "20260321131923": [
      "数学",
      "思维",
      "知识点::数学::三角函数::三角恒等变换::二倍角公式",
      "能力素养::数学::逻辑推理",
      "题型::选择题::单项选择题::高考真题",
      "知识点::数学::三角函数::同角三角函数基本关系",
      "难度::基础::多公式综合应用",
      "能力素养::数学::运算求解",
      "知识点::数学::三角函数::弦切互化",
      "打印::数学::原三角函数"
    ],
    "20260321131958": [
      "数学",
      "思维",
      "能力素养::数学::逻辑推理",
      "难度::中档::多公式综合化简",
      "题型::选择题::单项选择题::高考真题",
      "知识点::数学::三角函数::三角恒等变换::辅助角公式",
      "知识点::数学::三角函数::同角三角函数基本关系",
      "知识点::数学::三角函数::三角恒等变换::两角和与差公式",
      "能力素养::数学::运算求解",
      "打印::数学::原三角函数"
    ],
    "20260321134409": [
      "数学",
      "思维",
      "知识点::数学::三角函数::三角恒等变换::和差角公式",
      "能力素养::数学::逻辑推理",
      "难度::中档::多考点综合::高考真题",
      "题型::选择题::单项选择题::高考真题",
      "知识点::数学::三角函数::同角三角函数基本关系::商数关系",
      "能力素养::数学::运算求解",
      "知识点::数学::三角函数::三角函数式化简求值",
      "打印::数学::原三角函数"
    ],
    "20260321134440": [
      "数学",
      "思维",
      "知识点::数学::三角函数::三角恒等变换::二倍角公式",
      "知识点::数学::三角函数::三角恒等变换::诱导公式",
      "能力素养::数学::逻辑推理",
      "能力素养::数学::运算求解能力",
      "难度::中档::多公式综合应用",
      "知识点::数学::三角函数::三角恒等变换::给值求值",
      "题型::选择题::高考真题",
      "题型::选择题::单项选择题",
      "打印::数学::原三角函数"
    ],
    "20260321134514": [
      "数学",
      "思维",
      "知识点::数学::三角函数::诱导公式",
      "能力素养::数学::逻辑推理",
      "知识点::数学::三角恒等变换::化简求值",
      "难度::中档::多考点综合",
      "能力素养::数学::数学运算",
      "题型::填空题::三角函数计算",
      "知识点::数学::三角函数::二倍角公式",
      "打印::数学::原三角函数"
    ],
    "20260321134636": [
      "数学",
      "思维",
      "题型::填空题::高考真题",
      "知识点::数学::三角函数::三角恒等变换::诱导公式应用",
      "能力素养::数学::逻辑推理",
      "能力素养::数学::运算求解能力",
      "难度::中档::多知识点综合",
      "知识点::数学::三角函数::象限角的三角函数符号判断",
      "知识点::数学::三角函数::同角三角函数基本关系",
      "打印::数学::原三角函数"
    ],
    "20260321134740": [
      "数学",
      "思维",
      "知识点::数学::三角函数::两角和的正切公式",
      "能力素养::数学::运算求解能力",
      "知识点::数学::三角函数::齐次式化简求值",
      "题型::解答题::三角函数计算",
      "题型::解答题::高考真题",
      "知识点::数学::三角函数::同角三角函数基本关系",
      "难度::基础::多公式综合应用",
      "知识点::数学::三角函数::二倍角公式",
      "能力素养::数学::逻辑推理能力",
      "打印::数学::原三角函数"
    ],
    "20260321134943": [
      "数学",
      "思维",
      "知识点::数学::解三角形::三角形内角和定理",
      "知识点::数学::解三角形::正弦定理",
      "能力素养::数学::逻辑推理",
      "难度::容易::基础公式应用",
      "能力素养::数学::数学运算",
      "题型::选择题::单项选择题",
      "打印::数学::原三角函数"
    ],
    "20260321135221": [
      "数学",
      "思维",
      "知识点::数学::必修五::解三角形::正弦定理",
      "题型::填空题::高考真题",
      "知识点::数学::必修五::解三角形::三角形面积公式",
      "能力素养::数学::逻辑推理",
      "难度::中档::多公式综合应用",
      "知识点::数学::必修五::解三角形::余弦定理",
      "能力素养::数学::运算求解",
      "打印::数学::原三角函数"
    ],
    "20260321135310": [
      "数学",
      "思维",
      "知识点::数学::解三角形::正弦定理",
      "知识点::数学::解三角形::余弦定理",
      "能力素养::数学::逻辑推理",
      "题型::解答题::解三角形综合题",
      "难度::中档::高考真题::多小问综合",
      "知识点::数学::解三角形::三角形面积计算",
      "能力素养::数学::运算求解",
      "打印::数学::原三角函数"
    ],
    "20260321135411": [
      "数学",
      "思维",
      "知识点::数学::解三角形::正弦定理",
      "知识点::数学::三角函数::两角和的正弦公式",
      "知识点::数学::解三角形::余弦定理",
      "能力素养::数学::逻辑推理",
      "难度::中档::双小问综合",
      "知识点::数学::解三角形::三角形面积计算",
      "题型::解答题::解三角形::高考真题",
      "能力素养::数学::数学运算",
      "打印::数学::原三角函数"
    ],
    "20260321140002": [
      "思维",
      "知识点::化学::化学反应原理::沉淀溶解平衡::pH与离子浓度计算",
      "知识点::化学::物质结构与性质::核外电子排布::价层电子排布式书写",
      "知识点::化学::化学工艺流程::多金属资源提取::分离提纯",
      "能力素养::化学::证据推理与模型认知",
      "难度::较难::高考真题::多模块综合",
      "知识点::化学::化学反应原理::物质分离提纯::萃取操作"
    ],
    "20260321140422": [
      "思维",
      "难度::中档::高考真题::多考点综合",
      "能力素养::化学::变化观念与平衡思想",
      "知识点::化学::工业流程::工业废盐回收利用",
      "知识点::化学::化学反应原理::溶度积(Ksp)计算",
      "知识点::化学::化学用语::离子方程式书写",
      "知识点::化学::化学用语::化学方程式书写"
    ],
    "20260321140841": [
      "思维",
      "题型::非选择题::工业流程题::铬盐制备流程",
      "能力素养::化学::变化观念与平衡思想",
      "知识点::化学::元素化合物::铝硅镁及其化合物的性质",
      "知识点::化学::化学反应原理::氧化还原反应",
      "能力素养::化学::科学态度与社会责任",
      "知识点::化学::元素化合物::铬及其化合物的转化",
      "知识点::化学::化学实验::工业流程分析::物质分离与提纯"
    ],
    "20260321141041": [
      "思维",
      "能力素养::化学::变化观念与平衡思想",
      "知识点::化学::氧化还原反应::化学方程式书写",
      "能力素养::化学::证据推理与模型认知",
      "知识点::化学::物质结构::化合价判断",
      "知识点::化学::化学工艺流程::贵金属回收提纯"
    ],
    "20260321141148": [
      "思维",
      "知识点::化学::化学工艺流程::贵金属提取",
      "题型::解答题::工艺流程综合题",
      "知识点::化学::晶体结构与性质::晶胞配位数判断",
      "能力素养::化学::证据推理与模型认知",
      "能力素养::思维::逻辑推理",
      "知识点::化学::晶体结构与性质::晶胞密度计算"
    ],
    "20260321141410": [
      "思维",
      "知识点::化学::化学用语::化学反应方程式书写",
      "知识点::化学::化学反应原理::沉淀溶解平衡::溶度积Ksp计算",
      "能力素养::化学::思维::综合分析能力",
      "能力素养::化学::证据推理与模型认知",
      "能力素养::化学::科学探究与创新意识",
      "知识点::化学::化学实验::物质分离提纯::结晶操作选择"
    ],
    "20260321141544": [
      "思维",
      "知识点::化学::化学反应原理::难溶电解质溶解平衡::Ksp应用",
      "知识点::化学::化学实验::工业工艺流程::金属回收",
      "题型::非选择题::工业流程大题",
      "能力素养::化学::证据推理与模型认知",
      "知识点::化学::有机化学::手性碳原子判断",
      "知识点::化学::化学反应原理::盐类水解平衡"
    ],
    "20260321142429": [
      "思维",
      "能力素养::化学::变化观念与平衡思想",
      "知识点::化学::化学反应原理::氧化还原反应",
      "知识点::化学::化学反应原理::弱电解质电离平衡",
      "知识点::化学::离子反应::离子方程式书写",
      "能力素养::化学::证据推理与模型认知",
      "知识点::化学::物质结构与性质::晶胞结构与掺杂分析"
    ],
    "20260321142607": [
      "思维",
      "知识点::化学::基本概念::化合价计算",
      "难度::中档::多考点综合::含定量计算",
      "知识点::化学::物质变化::物态变化::凝华",
      "能力素养::化学::证据推理与模型认知",
      "知识点::化学::化学用语::化学方程式书写",
      "知识点::化学::原子结构::核外电子排布式书写",
      "题型::解答题::化工流程题::物质制备类"
    ],
    "20260321142812": [
      "思维",
      "能力素养::化学::变化观念与平衡思想",
      "题型::解答题::工业流程综合题",
      "能力素养::化学::思维::综合推理分析",
      "能力素养::化学::证据推理与模型认知",
      "知识点::化学::化学反应原理::沉淀溶解平衡::沉淀转化离子方程式书写",
      "知识点::化学::物质结构与性质::原子核外价电子排布式书写"
    ],
    "20260321142924": [
      "思维",
      "题型::非选择题::电化学与工艺流程综合题",
      "知识点::化学::氧化还原反应::化学方程式书写",
      "难度::中档::多考点综合应用",
      "能力素养::化学::宏观辨识与微观探析",
      "知识点::化学::物质结构与性质::离子空间构型判断",
      "能力素养::化学::科学思维与应用"
    ],
    "20260321143126": [
      "思维",
      "知识点::化学::化学与STSE::绿色化学",
      "题型::解答题::化学工艺流程题",
      "知识点::化学::溶液中的离子平衡::溶度积Ksp计算",
      "能力素养::化学::科学态度与社会责任",
      "知识点::化学::物质结构与性质::晶胞计算",
      "能力素养::化学::科学探究与创新意识",
      "知识点::化学::电化学::电解池原理"
    ],
    "20260321143245": [
      "思维",
      "知识点::化学::物质结构与性质::晶胞密度计算",
      "题型::解答题::高考真题::化工流程与物质结构综合题",
      "知识点::化学::物质结构与性质::晶胞粒子间距计算",
      "能力素养::化学::科学态度与社会责任",
      "知识点::化学::化学反应方程式::氧化还原反应方程式配平书写"
    ],
    "20260321143435": [
      "思维",
      "能力素养::化学::科学思维::工艺流程综合分析",
      "题型::解答题::化学工艺流程题",
      "知识点::化学::氧化还原反应::陌生方程式书写",
      "能力素养::化学::证据推理与模型认知",
      "知识点::化学::物质分离与提纯::焙烧、水浸、萃取操作"
    ],
    "20260321143627": [
      "思维",
      "知识点::化学::化学计算::滴定相关质量分数计算",
      "知识点::化学::化学实验::定量实验::氧化还原滴定",
      "知识点::化学::元素化合物::锗及其化合物性质",
      "知识点::化学::化学用语::氧化还原反应方程式配平",
      "能力素养::化学::证据推理与模型认知",
      "知识点::化学::物质分类::两性氧化物判定",
      "题型::非选择题::工业流程综合题::结合滴定实验考查"
    ],
    "20260321143808": [
      "思维",
      "难度::中档::多平衡常数综合运算",
      "知识点::化学::化学反应原理::水溶液中的离子平衡::沉淀溶解平衡::溶度积(Ksp)计算",
      "题型::选择题::单项选择题::高考化学真题",
      "知识点::化学::化学反应原理::水溶液中的离子平衡::盐类水解常数计算"
    ],
    "20260321143906": [
      "思维",
      "能力素养::化学::变化观念与平衡思想",
      "能力素养::化学::证据推理与模型认知",
      "知识点::化学::化学反应原理::溶液中的离子平衡::离子浓度大小比较",
      "题型::选择题::单项选择题::化学原理图像题"
    ],
    "20260321144008": [
      "思维",
      "能力素养::化学::变化观念与平衡思想",
      "题型::高考真题::2025云南卷",
      "知识点::化学::化学反应原理::水溶液中的离子平衡::电离平衡常数计算",
      "知识点::化学::化学反应原理::水溶液中的离子平衡::粒子浓度大小比较",
      "知识点::化学::化学反应原理::水溶液中的离子平衡::微粒分布分数图像分析"
    ],
    "20260321144104": [
      "思维",
      "题型::选择题::单项选择题::高考化学真题::选非题",
      "能力素养::化学::思维::证据推理与模型认知",
      "知识点::化学::化学反应原理::沉淀溶解平衡::溶度积Ksp应用",
      "能力素养::化学::宏观辨识与微观探析"
    ],
    "20260321144158": [
      "思维",
      "知识点::化学::物质结构与性质::配位化合物::配合物稳定常数计算",
      "难度::较难::高考真题::多考点综合",
      "知识点::化学::化学反应原理::水溶液中的离子平衡::粒子浓度大小比较",
      "知识点::化学::化学反应原理::水溶液中的离子平衡::分布系数图像分析"
    ],
    "20260321144257": [
      "思维",
      "知识点::化学::化学反应原理::配位平衡::稳定常数计算",
      "知识点::化学::物质结构与性质::配合物的结构与性质",
      "知识点::化学::化学反应原理::水溶液中的离子平衡::物种分布曲线分析",
      "难度::较难::多考点综合::图像分析与计算结合"
    ],
    "20260321144340": [
      "思维",
      "难度::中档::高考真题::多考点综合",
      "能力素养::化学::思维::逻辑推理",
      "题型::选择题::单项选择题::化工流程与离子平衡综合",
      "能力素养::化学::证据推理与模型认知",
      "知识点::化学::化学反应原理::盐类的水解"
    ],
    "20260321144408": [
      "思维",
      "能力素养::化学::变化观念与平衡思想",
      "知识点::化学::化学反应原理::配位平衡::外界条件对平衡移动的影响",
      "知识点::化学::化学反应原理::水溶液中的离子平衡::电离方程式正误判断"
    ],
    "20260321144500": [
      "思维",
      "能力素养::化学::变化观念与平衡思想::平衡移动与浓度变化分析",
      "题型::选择题::单项选择题::化学图像类选择题",
      "知识点::化学::化学反应原理::配位平衡::配合物平衡常数计算"
    ],
    "20260321144548": [
      "思维",
      "知识点::化学::水溶液中的离子平衡::配位平衡计算",
      "能力素养::化学::思维::证据推理与模型认知",
      "难度::较难::多考点综合::图像分析",
      "知识点::化学::水溶液中的离子平衡::盐类水解::水解常数应用"
    ],
    "20260321144645": [
      "思维",
      "能力素养::化学::变化观念与平衡思想",
      "知识点::化学::化学反应原理::难溶电解质的溶解平衡::Ksp计算",
      "难度::中档::多考点综合"
    ],
    "20260321144724": [
      "思维",
      "知识点::化学::化学反应原理::难溶电解质的溶解平衡::溶度积(Ksp)计算与应用",
      "知识点::化学::化学反应原理::化学平衡::平衡常数计算",
      "题型::选择题::单项选择题::溶解平衡图像类选择题",
      "知识点::化学::元素化合物::金属及其化合物::两性氢氧化物的性质",
      "知识点::化学::化学反应原理::难溶电解质的溶解平衡::离子分离与提纯"
    ],
    "20260321144813": [
      "思维",
      "能力素养::化学::科学探究",
      "知识点::化学::化学反应原理::水溶液中的离子平衡::离子浓度大小比较",
      "难度::中档::多考点综合",
      "知识点::化学::配位化合物::银氨络离子的形成"
    ],
    "20260328150917": [
      "数学",
      "思维",
      "知识点::数学::选择性必修第一册::圆锥曲线::椭圆标准方程求解",
      "能力素养::数学::逻辑推理",
      "能力素养::数学::直观想象",
      "知识点::数学::选择性必修第一册::圆锥曲线::椭圆离心率计算",
      "知识点::数学::选择性必修第一册::圆锥曲线::椭圆中的最值问题",
      "知识点::数学::选择性必修第一册::圆锥曲线::椭圆中的面积比值计算",
      "题型::解答题::圆锥曲线::椭圆综合大题",
      "能力素养::数学::数学运算",
      "知识点::数学::选择性必修第一册::圆锥曲线::椭圆的几何性质",
      "难度::较难::多小问多考点综合",
      "打印::数学::原三角函数"
    ],
    "20260405151708": [
      "数学",
      "打印::数学::一4/5"
    ],
    "20260405151718": [
      "数学",
      "打印::数学::一4/5"
    ],
    "20260405151733": [
      "数学",
      "打印::数学::一4/5"
    ],
    "20260405152021": [
      "数学",
      "打印::数学::一4/5"
    ],
    "20260405152034": [
      "数学",
      "打印::数学::一4/5"
    ],
    "20260405152047": [
      "数学",
      "打印::数学::一4/5"
    ],
    "20260405152103": [
      "数学",
      "打印::数学::一4/5"
    ],
    "20260405152110": [
      "数学",
      "打印::数学::一4/5"
    ],
    "20260405152144": [
      "数学",
      "打印::数学::一4/5"
    ],
    "20260405152156": [
      "数学",
      "打印::数学::一4/5"
    ],
    "20260405152204": [
      "数学",
      "打印::数学::一4/5"
    ],
    "20260405152221": [
      "数学",
      "打印::数学::一4/5"
    ],
    "20260405152225": [
      "数学",
      "打印::数学::一4/5"
    ],
    "20260405152232": [
      "数学",
      "打印::数学::一4/5"
    ],
    "20260405152242": [
      "数学",
      "打印::数学::一4/5"
    ],
    "20260405152326": [
      "数学",
      "打印::数学::一4/5"
    ],
    "20260405152340": [
      "数学",
      "打印::数学::一4/5"
    ],
    "20260405152357": [
      "数学",
      "打印::数学::一4/5"
    ],
    "20260405152403": [
      "数学",
      "打印::数学::一4/5"
    ],
    "20260405152514": [
      "数学",
      "打印::数学::一4/5"
    ],
    "20260405152522": [
      "数学",
      "打印::数学::一4/5"
    ],
    "20260405152530": [
      "数学",
      "打印::数学::一4/5"
    ],
    "20260405152542": [
      "数学",
      "打印::数学::一4/5"
    ],
    "20260405152552": [
      "数学",
      "打印::数学::一4/5"
    ],
    "20260405152600": [
      "数学",
      "打印::数学::一4/5"
    ],
    "20260405152607": [
      "数学",
      "打印::数学::一4/5"
    ],
    "20260405152617": [
      "数学",
      "打印::数学::一4/5"
    ],
    "20260405152626": [
      "数学",
      "打印::数学::一4/5"
    ],
    "20260405152633": [
      "数学",
      "打印::数学::一4/5"
    ],
    "20260405152651": [
      "数学",
      "打印::数学::一4/5"
    ],
    "20260405152659": [
      "数学",
      "打印::数学::一4/5"
    ],
    "20260405152703": [
      "数学",
      "打印::数学::一4/5"
    ],
    "20260405152707": [
      "数学",
      "打印::数学::一4/5"
    ],
    "20260405152714": [
      "数学",
      "打印::数学::一4/5"
    ],
    "20260405152722": [
      "数学",
      "打印::数学::一4/5"
    ],
    "20260405152733": [
      "数学",
      "打印::数学::一4/5"
    ],
    "20260405152741": [
      "数学",
      "打印::数学::一4/5"
    ],
    "20260405152749": [
      "数学",
      "打印::数学::一4/5"
    ],
    "20260405152844": [
      "数学",
      "打印::数学::一4/5"
    ],
    "20260405152854": [
      "数学",
      "打印::数学::一4/5"
    ],
    "20260405152912": [
      "数学",
      "打印::数学::一4/5"
    ],
    "20260405152925": [
      "数学",
      "打印::数学::一4/5"
    ],
    "20260405153002": [
      "数学",
      "打印::数学::一4/5"
    ],
    "20260405153009": [
      "数学",
      "打印::数学::一4/5"
    ],
    "20260405153024": [
      "数学",
      "打印::数学::一4/5"
    ],
    "20260405153051": [
      "数学",
      "打印::数学::一4/5"
    ],
    "20260405153105": [
      "数学",
      "打印::数学::一4/5"
    ],
    "20260405153115": [
      "数学",
      "打印::数学::一4/5"
    ],
    "20260405153128": [
      "数学",
      "打印::数学::一4/5"
    ],
    "20260405153139": [
      "数学",
      "打印::数学::一4/5"
    ],
    "20260405153147": [
      "数学",
      "打印::数学::一4/5"
    ],
    "20260405153210": [
      "数学",
      "打印::数学::一4/5"
    ],
    "20260405153216": [
      "数学",
      "打印::数学::一4/5"
    ],
    "20260405153252": [
      "数学",
      "打印::数学::一4/5"
    ],
    "20260405153325": [
      "数学",
      "打印::数学::一4/5"
    ],
    "20260405153342": [
      "数学",
      "打印::数学::一4/5"
    ],
    "20260405153350": [
      "数学",
      "打印::数学::一4/5"
    ],
    "20260405153358": [
      "数学",
      "打印::数学::一4/5"
    ],
    "20260405153408": [
      "数学",
      "打印::数学::一4/5"
    ],
    "20260405153416": [
      "数学",
      "打印::数学::一4/5"
    ],
    "20260405153428": [
      "数学",
      "打印::数学::一4/5"
    ],
    "20260405153436": [
      "数学",
      "打印::数学::一4/5"
    ],
    "20260405153448": [
      "数学",
      "打印::数学::一4/5"
    ],
    "20260405153500": [
      "数学",
      "打印::数学::一4/5"
    ],
    "20260405204354": [
      "化学"
    ],
    "20260405204451": [
      "化学"
    ],
    "20260405204502": [
      "化学"
    ],
    "20260405204514": [
      "化学"
    ],
    "20260405204528": [
      "化学"
    ],
    "20260405204539": [
      "化学"
    ],
    "20260405204606": [
      "化学"
    ],
    "20260405204652": [
      "化学"
    ],
    "20260405204716": [
      "化学"
    ],
    "20260405205119": [
      "化学"
    ],
    "20260405205127": [
      "化学"
    ],
    "20260405205143": [
      "化学"
    ],
    "20260405205157": [
      "化学"
    ],
    "20260405205204": [
      "化学"
    ],
    "20260405205213": [
      "化学"
    ],
    "20260405205226": [
      "化学"
    ],
    "20260405205234": [
      "化学"
    ],
    "20260405205551": [
      "化学"
    ],
    "20260405205604": [
      "化学"
    ],
    "20260405210619": [
      "化学"
    ],
    "20260405210626": [
      "化学"
    ],
    "20260405210637": [
      "化学"
    ],
    "20260405210648": [
      "化学"
    ],
    "20260405210655": [
      "化学"
    ],
    "20260405210711": [
      "化学"
    ],
    "20260405210936": [
      "化学"
    ],
    "20260405211003": [
      "化学"
    ],
    "20260405211026": [
      "化学"
    ],
    "20260405211050": [
      "化学"
    ],
    "20260405211056": [
      "化学"
    ],
    "20260405211106": [
      "化学"
    ],
    "20260405211114": [
      "化学"
    ],
    "20260405211137": [
      "化学"
    ],
    "20260405211148": [
      "化学"
    ],
    "20260405211156": [
      "化学"
    ],
    "20260405211214": [
      "化学"
    ],
    "20260405211224": [
      "化学"
    ],
    "20260405211232": [
      "化学"
    ],
    "20260405211242": [
      "化学"
    ],
    "20260405211323": [
      "化学"
    ],
    "20260405211346": [
      "化学"
    ],
    "20260405211413": [
      "化学"
    ],
    "20260405211418": [
      "化学"
    ],
    "20260405211425": [
      "化学"
    ],
    "20260405211438": [
      "化学"
    ],
    "20260405211458": [
      "化学"
    ],
    "20260405211504": [
      "化学"
    ],
    "20260405211513": [
      "化学"
    ],
    "20260405211521": [
      "化学"
    ],
    "20260405211529": [
      "化学"
    ],
    "20260405211540": [
      "化学"
    ],
    "20260405211550": [
      "化学"
    ],
    "20260405211559": [
      "化学"
    ],
    "20260405211609": [
      "化学"
    ],
    "20260405211620": [
      "化学"
    ],
    "20260405211641": [
      "化学"
    ],
    "20260405211704": [
      "化学"
    ],
    "20260405211720": [
      "化学"
    ],
    "20260405211739": [
      "化学"
    ],
    "20260405211753": [
      "化学"
    ],
    "20260405211826": [
      "化学"
    ],
    "20260405211832": [
      "化学"
    ],
    "20260405211842": [
      "化学"
    ],
    "20260405211851": [
      "化学"
    ],
    "20260405211856": [
      "化学"
    ],
    "20260405211902": [
      "化学"
    ],
    "20260405211910": [
      "化学"
    ],
    "20260405211921": [
      "化学"
    ],
    "20260405211927": [
      "化学"
    ],
    "20260405211935": [
      "化学"
    ],
    "20260405211949": [
      "化学"
    ],
    "20260405211959": [
      "化学"
    ],
    "20260405212013": [
      "化学"
    ],
    "20260405212037": [
      "化学"
    ],
    "20260405212108": [
      "化学"
    ],
    "20260405212139": [
      "化学"
    ],
    "20260405212155": [
      "化学"
    ]
  },
  "tag_tree": {
    "生物": {},
    "积累": {},
    "知识点": {
      "children": {
        "生物": {
          "children": {
            "生态系统": {
              "children": {
                "食物链与食物网": {
                  "children": {
                    "营养级": {}
                  }
                },
                "能量流动": {
                  "children": {
                    "生长发育繁殖能量计算": {},
                    "同化量与摄入量关系": {},
                    "流经生态系统总能量判断": {},
                    "能量传递效率计算": {},
                    "粪便能量归属": {},
                    "能量传递效率与利用率辨析": {},
                    "流入生态系统的总能量": {},
                    "能量流动过程分析": {},
                    "同化量计算": {},
                    "能量流动的去路": {},
                    "能量流动的去向": {},
                    "能量流动的意义": {},
                    "生产者能量去向": {}
                  }
                },
                "生物富集作用": {},
                "物质循环": {
                  "children": {
                    "碳循环": {}
                  }
                },
                "能量流动的特点": {},
                "生态系统的组成成分": {},
                "生物群落的定义": {},
                "物种丰富度调查方法": {},
                "生物多样性的价值": {},
                "稳定性": {
                  "children": {
                    "抵抗力稳定性": {}
                  }
                },
                "湿地生态系统": {
                  "children": {
                    "蓝碳生态系统": {}
                  }
                },
                "物质循环的过程": {},
                "能量流动的特点与传递效率": {},
                "能量流动的实践应用": {},
                "碳循环": {},
                "生产者与消费者功能": {},
                "生态系统的稳定性": {
                  "children": {
                    "抵抗力稳定性": {}
                  }
                },
                "食物链书写": {},
                "组成成分": {
                  "children": {
                    "生产者": {}
                  }
                },
                "生态系统的结构": {
                  "children": {
                    "营养级": {}
                  }
                },
                "微生物分解作用": {},
                "种间关系": {
                  "children": {
                    "生态位": {}
                  }
                },
                "物质循环与能量流动的关系": {},
                "生态系统结构": {
                  "children": {
                    "营养级判定": {},
                    "食物链与食物网": {}
                  }
                },
                "生态系统功能": {
                  "children": {
                    "能量流动规律": {}
                  }
                },
                "生态系统合理利用": {},
                "种间互作实验分析": {}
              }
            },
            "生态与环境": {
              "children": {
                "环境胁迫": {},
                "生态足迹": {
                  "children": {
                    "减少生态足迹的措施": {}
                  }
                },
                "生物多样性及其保护": {},
                "可持续发展理念": {},
                "生态系统破碎化的影响": {}
              }
            },
            "种群": {
              "children": {
                "环境容纳量": {},
                "种群数量变化": {
                  "children": {
                    "S型增长与环境容纳量": {},
                    "S型增长": {},
                    "环境容纳量(K值)": {}
                  }
                },
                "种群生存风险分析": {},
                "种群密度变化分析": {},
                "种群数量变化的影响因素": {},
                "种群数量计算": {},
                "种群密度调查": {
                  "children": {
                    "样方法": {}
                  }
                }
              }
            },
            "生命活动调节": {
              "children": {
                "稳态调节": {}
              }
            },
            "稳态与环境": {
              "children": {
                "生态系统": {
                  "children": {
                    "能量流动": {
                      "children": {
                        "营养级能量去向": {},
                        "能量流动的特点": {}
                      }
                    },
                    "生态系统的结构": {},
                    "信息传递": {},
                    "物质循环": {},
                    "负反馈调节": {},
                    "生态系统稳定性": {
                      "children": {
                        "抵抗力稳定性": {}
                      }
                    },
                    "生态系统自我调节能力": {},
                    "食物链与营养级": {},
                    "生态系统的稳定性": {},
                    "食物链与食物网": {
                      "children": {
                        "营养级判断": {}
                      }
                    },
                    "人类活动对生态系统的影响": {},
                    "生态承载力与生态盈余": {},
                    "生态足迹概念": {}
                  }
                },
                "生物多样性": {
                  "children": {
                    "间接价值": {}
                  }
                },
                "生态系统稳定性": {},
                "种间关系": {},
                "生态保护": {
                  "children": {
                    "生物多样性保护": {}
                  }
                },
                "群落": {
                  "children": {
                    "生态位": {
                      "children": {
                        "研究内容与意义": {}
                      }
                    },
                    "群落演替": {}
                  }
                },
                "生态工程": {
                  "children": {
                    "生态学基本原理": {},
                    "生态工程基本原理": {}
                  }
                },
                "生态系统的物质循环": {
                  "children": {
                    "碳循环": {}
                  }
                },
                "生物多样性的保护措施": {},
                "生态系统功能": {
                  "children": {
                    "物质循环": {},
                    "能量流动": {}
                  }
                }
              }
            },
            "必修三": {
              "children": {
                "生态系统": {
                  "children": {
                    "生态系统稳定性": {}
                  }
                },
                "生态系统保护": {},
                "生物多样性": {
                  "children": {
                    "协同进化": {}
                  }
                },
                "种间关系": {
                  "children": {
                    "互利共生": {}
                  }
                }
              }
            },
            "生态学": {
              "children": {
                "种群的特征": {},
                "生态系统的功能": {
                  "children": {
                    "物质循环与能量流动": {}
                  }
                },
                "群落演替": {},
                "可持续发展": {},
                "生态系统保护": {
                  "children": {
                    "生态工程原理": {}
                  }
                },
                "生态系统的稳定性": {
                  "children": {
                    "自我调节能力": {}
                  }
                }
              }
            },
            "生态农业": {
              "children": {
                "原理应用": {},
                "管理措施效益分析": {},
                "常见生态农业模式": {}
              }
            },
            "群落": {
              "children": {
                "群落空间结构": {},
                "物种丰富度": {},
                "群落的空间结构": {
                  "children": {
                    "垂直结构": {}
                  }
                },
                "群落特征与演替": {},
                "群落演替": {
                  "children": {
                    "次生演替": {}
                  }
                },
                "群落的特征": {
                  "children": {
                    "物种组成": {}
                  }
                },
                "空间结构": {
                  "children": {
                    "水平结构": {}
                  }
                },
                "群落的结构": {
                  "children": {
                    "水平结构": {}
                  }
                },
                "群落结构": {
                  "children": {
                    "空间结构": {}
                  }
                },
                "种间关系": {}
              }
            },
            "生态系统组成成分": {
              "children": {
                "分解者": {}
              }
            },
            "生态保护": {
              "children": {
                "植被水土保持作用": {},
                "可持续发展理念": {},
                "就地保护与易地保护辨析": {},
                "气候变化对生境的影响": {}
              }
            },
            "光合作用": {
              "children": {
                "影响光合作用的环境因素": {}
              }
            },
            "害虫防治": {
              "children": {
                "生物防治": {}
              }
            },
            "生态系统与环境保护": {
              "children": {
                "生物多样性及其价值": {},
                "生态系统的稳定性与自我调节": {}
              }
            },
            "生态系统的结构": {
              "children": {
                "食物网": {}
              }
            },
            "细胞代谢": {
              "children": {
                "细胞呼吸": {
                  "children": {
                    "无氧呼吸": {}
                  }
                }
              }
            },
            "生物与环境": {
              "children": {
                "生态系统": {
                  "children": {
                    "能量流动": {
                      "children": {
                        "林德曼能量流动研究": {},
                        "能量流动的特点": {}
                      }
                    },
                    "种间关系": {
                      "children": {
                        "捕食的意义": {}
                      }
                    },
                    "栖息地对物种分布的影响": {}
                  }
                },
                "生物与环境的相互关系": {},
                "生物多样性的价值": {
                  "children": {
                    "直接价值": {},
                    "间接价值": {}
                  }
                },
                "种群": {
                  "children": {
                    "种群密度调查方法": {
                      "children": {
                        "样线法": {}
                      }
                    }
                  }
                },
                "生物多样性": {
                  "children": {
                    "易地保护": {},
                    "物种多样性调查": {}
                  }
                },
                "群落": {
                  "children": {
                    "群落结构": {}
                  }
                },
                "生物多样性的层次判断": {},
                "生物对环境的适应性": {},
                "种间关系": {
                  "children": {
                    "互利共生与寄生辨析": {}
                  }
                },
                "全球性生态环境问题": {
                  "children": {
                    "水华治理": {}
                  }
                },
                "生态系统的稳定性": {},
                "生态工程的基本原理": {},
                "生物入侵": {},
                "生态修复": {
                  "children": {
                    "水体富营养化治理": {}
                  }
                },
                "种群特征": {
                  "children": {
                    "年龄结构": {}
                  }
                },
                "物质循环": {
                  "children": {
                    "N、P元素循环": {}
                  }
                }
              }
            },
            "生态环境保护": {
              "children": {
                "生态足迹": {},
                "碳中和": {}
              }
            },
            "生态修复": {
              "children": {
                "长江禁渔政策相关考点": {}
              }
            },
            "可持续发展": {
              "children": {
                "生态保护实践措施": {}
              }
            },
            "生态与环境保护": {
              "children": {
                "生物多样性保护": {
                  "children": {
                    "易地保护": {}
                  }
                }
              }
            },
            "生态工程": {
              "children": {
                "协调与平衡原理": {},
                "生态农业设计": {},
                "生态修复": {},
                "协调原理": {}
              }
            },
            "选择性必修二": {
              "children": {
                "生态系统及其稳定性": {
                  "children": {
                    "抵抗力稳定性": {},
                    "生态系统信息传递的类型": {},
                    "生物防治": {},
                    "生态系统信息传递的功能": {}
                  }
                },
                "生态环境保护": {
                  "children": {
                    "生态足迹与生态承载力": {}
                  }
                },
                "生态工程": {
                  "children": {
                    "基本原理": {
                      "children": {
                        "自生原理": {},
                        "整体性原理": {}
                      }
                    }
                  }
                },
                "生物与环境": {
                  "children": {
                    "生态系统的组成成分": {},
                    "生态系统的结构": {},
                    "生物多样性的价值": {},
                    "种间关系": {}
                  }
                }
              }
            },
            "生物多样性": {
              "children": {
                "生物多样性的意义": {},
                "生物多样性保护措施": {},
                "生物多样性的价值": {},
                "保护措施": {},
                "价值": {},
                "内涵": {}
              }
            },
            "种群与群落": {
              "children": {
                "种群数量特征": {},
                "种群数量变化影响因素": {}
              }
            },
            "生态系统及其稳定性": {
              "children": {
                "负反馈调节机制": {},
                "自我调节能力": {}
              }
            },
            "生物的进化": {
              "children": {
                "生殖隔离": {}
              }
            },
            "选择性必修2": {
              "children": {
                "生物与环境": {
                  "children": {
                    "生态工程的自生原理": {},
                    "生态系统的稳定性": {},
                    "生态平衡的维持": {}
                  }
                },
                "生态系统": {
                  "children": {
                    "生态系统稳定性": {},
                    "生态农业": {},
                    "能量流动": {},
                    "物质循环": {}
                  }
                }
              }
            },
            "生态系统的功能": {
              "children": {
                "信息传递": {
                  "children": {
                    "信息类型": {}
                  }
                }
              }
            },
            "生物多样性及其保护": {
              "children": {
                "保护措施": {},
                "生物多样性的价值": {}
              }
            },
            "生态环境": {
              "children": {
                "碳中和": {}
              }
            },
            "实验探究": {
              "children": {
                "对照实验结果分析": {},
                "生态学实验": {
                  "children": {
                    "结果分析": {}
                  }
                }
              }
            },
            "生态环境治理": {
              "children": {
                "水体富营养化治理": {}
              }
            },
            "生态系统的稳定性": {
              "children": {
                "抵抗力稳定性": {}
              }
            },
            "生物进化": {
              "children": {
                "协同进化": {}
              }
            },
            "实验与探究": {
              "children": {
                "实验结果数据分析": {}
              }
            },
            "选择性必修一": {
              "children": {
                "植物生命活动调节": {
                  "children": {
                    "光敏色素的作用": {}
                  }
                }
              }
            }
          }
        },
        "化学": {
          "children": {
            "化学与STSE": {
              "children": {
                "环境保护": {
                  "children": {
                    "碳达峰碳中和": {}
                  }
                },
                "绿色化学": {}
              }
            },
            "化学与能源资源开发利用": {},
            "物质结构与性质": {
              "children": {
                "杂化轨道理论": {
                  "children": {
                    "杂化类型判断": {}
                  }
                },
                "核外电子排布": {
                  "children": {
                    "价层电子排布式书写": {},
                    "基态原子价层电子排布式": {},
                    "基态离子电子排布式书写": {}
                  }
                },
                "配位化合物": {
                  "children": {
                    "配合物稳定常数计算": {}
                  }
                },
                "晶胞结构与掺杂分析": {},
                "配位键与超分子作用": {},
                "原子核外价电子排布式书写": {},
                "离子空间构型判断": {},
                "晶胞计算": {},
                "晶胞密度计算": {},
                "晶胞结构分析与化学式推导": {},
                "晶胞粒子间距计算": {},
                "配合物的结构与性质": {}
              }
            },
            "化学反应原理": {
              "children": {
                "沉淀溶解平衡": {
                  "children": {
                    "pH与离子浓度计算": {},
                    "溶度积Ksp计算": {},
                    "Ksp计算": {},
                    "沉淀转化离子方程式书写": {},
                    "溶度积Ksp应用": {},
                    "沉淀转化": {},
                    "溶度积(Ksp)比较": {}
                  }
                },
                "氧化还原反应": {
                  "children": {
                    "方程式书写": {}
                  }
                },
                "物质分离提纯": {
                  "children": {
                    "萃取操作": {}
                  }
                },
                "溶度积(Ksp)计算": {},
                "压强对气体溶解度的影响": {},
                "溶解度大小比较": {},
                "化学反应速率影响因素": {},
                "化学反应进行的方向判断": {},
                "难溶电解质溶解平衡": {
                  "children": {
                    "Ksp应用": {}
                  }
                },
                "离子方程式书写": {},
                "盐类水解平衡": {},
                "弱电解质电离平衡": {},
                "化学平衡移动分析": {},
                "化学平衡移动": {},
                "盐类水解": {
                  "children": {
                    "易水解盐无水物制备": {}
                  }
                },
                "化学反应速率": {
                  "children": {
                    "温度对反应速率的影响": {}
                  }
                },
                "电化学": {
                  "children": {
                    "二次电池": {
                      "children": {
                        "铅酸电池": {}
                      }
                    },
                    "电极反应式书写": {}
                  }
                },
                "化学方程式书写": {},
                "水溶液中的离子平衡": {
                  "children": {
                    "弱电解质电离常数计算": {},
                    "离子浓度关系": {
                      "children": {
                        "质子守恒": {}
                      }
                    },
                    "沉淀溶解平衡": {
                      "children": {
                        "溶度积(Ksp)计算": {}
                      }
                    },
                    "盐类水解常数计算": {},
                    "酸碱中和滴定计算": {},
                    "电离平衡常数计算": {},
                    "粒子浓度大小比较": {},
                    "微粒分布分数图像分析": {},
                    "弱电解质的电离": {},
                    "分布系数图像分析": {},
                    "物种分布曲线分析": {},
                    "质子守恒": {},
                    "电荷守恒": {},
                    "电离方程式正误判断": {},
                    "电荷守恒定律应用": {},
                    "离子浓度大小比较": {}
                  }
                },
                "弱电解质的电离": {
                  "children": {
                    "电离平衡常数应用": {},
                    "电离平衡常数计算": {},
                    "分布系数分析": {}
                  }
                },
                "溶液中的离子平衡": {
                  "children": {
                    "守恒关系应用": {},
                    "离子浓度大小比较": {}
                  }
                },
                "溶液离子平衡": {
                  "children": {
                    "离子浓度大小比较": {}
                  }
                },
                "电解质溶液": {
                  "children": {
                    "电荷守恒": {}
                  }
                },
                "配位平衡": {
                  "children": {
                    "稳定常数计算": {},
                    "外界条件对平衡移动的影响": {},
                    "配合物平衡常数计算": {}
                  }
                },
                "盐类的水解": {},
                "离子浓度大小比较": {},
                "难溶电解质的溶解平衡": {
                  "children": {
                    "Ksp计算": {},
                    "溶解平衡图像分析": {},
                    "溶度积(Ksp)计算与应用": {},
                    "沉淀溶解平衡图像分析": {},
                    "离子分离与提纯": {}
                  }
                },
                "化学平衡": {
                  "children": {
                    "平衡常数计算": {}
                  }
                }
              }
            },
            "化学工艺流程": {
              "children": {
                "多金属资源提取": {
                  "children": {
                    "分离提纯": {}
                  }
                },
                "贵金属回收提纯": {},
                "贵金属提取": {},
                "金属提取工艺": {}
              }
            },
            "元素化合物": {
              "children": {
                "非金属及其化合物": {
                  "children": {
                    "二氧化硅性质": {}
                  }
                },
                "锰及其化合物": {},
                "镁及其化合物": {},
                "铝硅镁及其化合物的性质": {},
                "铬及其化合物的转化": {},
                "金属及其化合物性质": {},
                "碳酸盐与酸的反应性质": {},
                "锗及其化合物性质": {},
                "金属及其化合物": {
                  "children": {
                    "两性氢氧化物性质": {},
                    "两性氢氧化物的性质": {}
                  }
                }
              }
            },
            "工业流程": {
              "children": {
                "工业废盐回收利用": {},
                "锗的提取工艺": {}
              }
            },
            "化学用语": {
              "children": {
                "离子方程式书写": {},
                "化学方程式书写": {},
                "化学方程式书写与配平": {},
                "化学反应方程式书写": {},
                "氧化还原反应方程式配平": {}
              }
            },
            "物质分离提纯": {
              "children": {
                "沉淀法除杂": {},
                "焙烧、水浸、酸浸操作应用": {}
              }
            },
            "化学实验": {
              "children": {
                "工业流程分析": {
                  "children": {
                    "物质分离与提纯": {}
                  }
                },
                "物质分离提纯": {
                  "children": {
                    "结晶操作选择": {},
                    "升华法除杂": {}
                  }
                },
                "工业工艺流程": {
                  "children": {
                    "金属回收": {},
                    "锶提取流程分析": {}
                  }
                },
                "pH调节试剂选择": {},
                "氧化还原滴定": {},
                "定量实验": {
                  "children": {
                    "氧化还原滴定": {}
                  }
                },
                "物质检验方法": {
                  "children": {
                    "原子发射光谱法": {}
                  }
                },
                "常见仪器识别": {
                  "children": {
                    "球形冷凝管": {}
                  }
                }
              }
            },
            "沉淀溶解平衡": {
              "children": {
                "溶度积(Ksp)计算": {},
                "溶度积Ksp计算": {}
              }
            },
            "化学计量": {
              "children": {
                "物质的量之比计算": {}
              }
            },
            "氧化还原反应": {
              "children": {
                "化学方程式书写": {},
                "氧化性强弱比较": {},
                "催化剂判断": {},
                "氧化剂与还原剂判断": {},
                "陌生方程式书写": {}
              }
            },
            "物质结构": {
              "children": {
                "化合价判断": {}
              }
            },
            "物质的分离与提纯": {
              "children": {
                "除杂": {}
              }
            },
            "原子结构": {
              "children": {
                "价层电子排布式书写": {},
                "核外电子排布式书写": {}
              }
            },
            "晶体结构与性质": {
              "children": {
                "晶胞配位数判断": {},
                "晶胞密度计算": {}
              }
            },
            "离子反应": {
              "children": {
                "离子方程式书写": {},
                "离子方程式配平": {}
              }
            },
            "化工流程": {
              "children": {
                "无机物制备工艺分析": {},
                "高纯硒制备流程": {},
                "有色金属冶炼烟尘回收工艺": {},
                "金属矿物分离提取": {},
                "有色金属废渣提取金属": {}
              }
            },
            "有机化学": {
              "children": {
                "手性碳原子判断": {}
              }
            },
            "工艺流程": {
              "children": {
                "金属化合物制备提纯": {},
                "废旧资源回收": {
                  "children": {
                    "试剂作用分析": {}
                  }
                }
              }
            },
            "基本概念": {
              "children": {
                "化合价计算": {}
              }
            },
            "物质变化": {
              "children": {
                "物态变化": {
                  "children": {
                    "凝华": {}
                  }
                }
              }
            },
            "化学计算": {
              "children": {
                "质量分数计算": {},
                "电化学电量相关计算": {},
                "滴定相关质量分数计算": {}
              }
            },
            "化学反应速率": {
              "children": {
                "影响因素": {}
              }
            },
            "溶液中的离子平衡": {
              "children": {
                "溶度积Ksp计算": {}
              }
            },
            "电化学": {
              "children": {
                "电解池原理": {}
              }
            },
            "化学反应方程式": {
              "children": {
                "氧化还原反应方程式配平书写": {}
              }
            },
            "水溶液中的离子平衡": {
              "children": {
                "溶度积(Ksp)计算": {},
                "弱电解质电离常数计算": {},
                "离子浓度比较": {
                  "children": {
                    "电荷守恒": {}
                  }
                },
                "配位平衡计算": {},
                "盐类水解": {
                  "children": {
                    "水解常数应用": {}
                  }
                }
              }
            },
            "物质分离与提纯": {
              "children": {
                "焙烧、水浸、萃取操作": {}
              }
            },
            "化学平衡": {
              "children": {
                "萃取平衡移动应用": {},
                "平衡常数计算": {}
              }
            },
            "物质分类": {
              "children": {
                "两性氧化物判定": {}
              }
            },
            "图像分析": {
              "children": {
                "pX-pH曲线分析": {}
              }
            },
            "配位化合物": {
              "children": {
                "银氨络离子的形成": {}
              }
            }
          }
        },
        "语文": {
          "children": {
            "现代文阅读": {
              "children": {
                "非连续性文本阅读": {
                  "children": {
                    "观点比较探究": {},
                    "论证思路与手法分析": {},
                    "内容理解与分析": {},
                    "词句表达效果赏析": {}
                  }
                },
                "论述类文本": {
                  "children": {
                    "内容理解分析": {},
                    "开放探究": {},
                    "观点正误判断": {},
                    "论据匹配": {},
                    "文本探究应用": {},
                    "内容理解与分析": {},
                    "核心观点概括": {},
                    "论证结构分析": {}
                  }
                },
                "现当代散文": {
                  "children": {
                    "内容要点概括": {},
                    "文学短评写作": {},
                    "文本内容理解": {},
                    "句子鉴赏分析": {}
                  }
                },
                "主旨意蕴探究": {},
                "内容理解分析": {},
                "艺术特色鉴赏": {},
                "表达技巧分析": {},
                "文学类文本阅读": {
                  "children": {
                    "小说阅读": {}
                  }
                },
                "散文": {
                  "children": {
                    "内容理解": {},
                    "艺术特色鉴赏": {},
                    "细节描写赏析": {},
                    "《到橘子林去》": {},
                    "标题作用分析": {},
                    "语言表达效果赏析": {},
                    "内容理解分析": {},
                    "书信体散文阅读": {},
                    "内容与艺术特色鉴赏": {},
                    "关键语句作用分析": {},
                    "文意理解与原因概括": {}
                  }
                },
                "多文本联动探究": {},
                "散文阅读": {
                  "children": {
                    "内容与艺术特色鉴赏": {},
                    "段落作用分析": {},
                    "物象内在联系分析": {},
                    "行文线索分析": {},
                    "内容理解": {},
                    "艺术特色鉴赏": {},
                    "描写作用分析": {},
                    "内容与艺术特色分析鉴赏": {},
                    "标题作用": {
                      "children": {
                        "全文统摄作用分析": {}
                      }
                    },
                    "叙述层次分析": {}
                  }
                },
                "句段作用分析": {},
                "情感意蕴探究": {},
                "内容理解与分析": {},
                "人物情感变化分析": {}
              }
            },
            "文化传承": {
              "children": {
                "中华优秀传统文化的创造性转化与创新性发展": {}
              }
            },
            "作家作品": {
              "children": {
                "沈从文": {}
              }
            }
          }
        },
        "数学": {
          "children": {
            "解三角形": {
              "children": {
                "正弦定理": {},
                "余弦定理": {},
                "内角计算": {},
                "余弦定理的应用": {},
                "夹角余弦值计算": {},
                "三角形内角和定理": {},
                "已知两边及一对角求未知角": {},
                "边角互化": {},
                "三角形面积公式": {},
                "同角三角函数基本关系": {},
                "三角形面积计算": {},
                "三角形三边关系": {},
                "三角形周长计算": {},
                "等边三角形边长计算": {}
              }
            },
            "三角函数": {
              "children": {
                "同角三角函数基本关系": {
                  "children": {
                    "商数关系": {}
                  }
                },
                "特殊角的三角函数值计算": {},
                "二倍角正弦公式": {},
                "象限角与三角函数符号判断": {},
                "两角和与差的正弦公式": {},
                "二倍角的余弦公式": {},
                "特殊角三角函数求值": {},
                "二倍角公式": {},
                "三角恒等变换": {
                  "children": {
                    "二倍角公式": {},
                    "辅助角公式": {},
                    "两角和与差公式": {},
                    "和差角公式": {},
                    "诱导公式": {},
                    "给值求值": {},
                    "诱导公式应用": {}
                  }
                },
                "弦切互化": {},
                "三角函数式化简求值": {},
                "诱导公式": {},
                "象限角的三角函数符号判断": {},
                "两角和的正切公式": {},
                "齐次式化简求值": {},
                "两角和的正弦公式": {}
              }
            },
            "三角形内角性质": {},
            "必修第五册": {
              "children": {
                "解三角形": {
                  "children": {
                    "余弦定理": {},
                    "正弦定理": {}
                  }
                }
              }
            },
            "必修五": {
              "children": {
                "解三角形": {
                  "children": {
                    "三角形面积公式": {},
                    "余弦定理": {},
                    "正弦定理": {}
                  }
                }
              }
            },
            "三角形内角和定理": {},
            "三角形": {
              "children": {
                "内角和定理": {}
              }
            },
            "三角恒等变换": {
              "children": {
                "正弦和差角公式": {},
                "两角和的正弦公式": {},
                "半角公式": {},
                "化简求值": {}
              }
            },
            "平面几何": {
              "children": {
                "圆的基本性质": {},
                "面积计算": {
                  "children": {
                    "扇形面积计算": {},
                    "三角形面积计算": {}
                  }
                },
                "圆": {
                  "children": {
                    "圆周角性质": {}
                  }
                }
              }
            },
            "数学文化": {
              "children": {
                "中国古代数学算法应用": {}
              }
            },
            "代数运算": {
              "children": {
                "公式代入求值": {}
              }
            },
            "最值问题": {
              "children": {
                "几何动态最值求解": {}
              }
            },
            "选择性必修第一册": {
              "children": {
                "圆锥曲线": {
                  "children": {
                    "椭圆标准方程求解": {},
                    "椭圆离心率计算": {},
                    "椭圆中的最值问题": {},
                    "椭圆中的面积比值计算": {},
                    "椭圆的几何性质": {}
                  }
                }
              }
            }
          }
        }
      }
    },
    "题型": {
      "children": {
        "选择题": {
          "children": {
            "单项选择题": {
              "children": {
                "高考真题": {},
                "图表信息类": {},
                "选考真题": {},
                "正误判断类": {},
                "高考选考真题": {},
                "高考模拟题": {},
                "正误判断题": {},
                "情境综合类": {},
                "选非题": {},
                "文本赏析正误判断": {},
                "高考文科真题": {},
                "高考化学真题": {
                  "children": {
                    "选非题": {}
                  }
                },
                "化学原理图像题": {},
                "化学图像题": {},
                "化工流程与离子平衡综合": {},
                "化学图像类选择题": {},
                "化学反应原理图像题": {},
                "溶解平衡图像类选择题": {},
                "化学实验探究类": {}
              }
            },
            "高考真题": {
              "children": {
                "2022湖北卷": {}
              }
            },
            "正误判断类": {},
            "多项选择题": {
              "children": {
                "高考真题": {}
              }
            },
            "时政情境类": {},
            "不定项选择题": {
              "children": {
                "表格信息类": {}
              }
            },
            "概念辨析类选择题": {},
            "图表分析类": {},
            "图像分析类": {}
          }
        },
        "高考真题": {
          "children": {
            "2023湖北卷": {},
            "天津卷": {
              "children": {
                "2022年": {}
              }
            },
            "2023年": {
              "children": {
                "全国乙卷": {},
                "湖北卷": {}
              }
            },
            "湖北卷": {
              "children": {
                "2022年": {}
              }
            },
            "2021年": {
              "children": {
                "全国甲卷": {}
              }
            },
            "辽宁卷": {
              "children": {
                "2022年": {}
              }
            },
            "2023湖南卷": {},
            "2025": {
              "children": {
                "湖南卷": {}
              }
            },
            "2025云南卷": {},
            "2025湖北卷": {}
          }
        },
        "图表信息题": {
          "children": {
            "表格数据分析": {}
          }
        },
        "解答题": {
          "children": {
            "生态类综合题": {},
            "生物简答题": {},
            "生物生态类综合题": {},
            "生物实验分析题": {},
            "生物非选择题": {
              "children": {
                "生态综合题": {}
              }
            },
            "表格信息分析题": {},
            "生物": {
              "children": {
                "生态类综合题": {}
              }
            },
            "生态学综合题": {},
            "图表信息分析题": {},
            "生物生态综合题": {},
            "生物填空题": {
              "children": {
                "图表信息分析": {}
              }
            },
            "现代文阅读": {
              "children": {
                "简答题": {}
              }
            },
            "现代文阅读主观题": {
              "children": {
                "观点探究": {},
                "语言效果分析": {}
              }
            },
            "简答题": {
              "children": {
                "物象关联分析": {},
                "结尾段落作用分析": {}
              }
            },
            "解三角形综合应用": {},
            "解三角形": {
              "children": {
                "综合计算": {},
                "高考真题": {}
              }
            },
            "证明+计算双设问": {},
            "解三角形类": {},
            "解三角形综合题": {},
            "三角函数计算": {},
            "高考真题": {
              "children": {
                "化工流程与物质结构综合题": {}
              }
            },
            "化工流程综合题": {},
            "工业流程题": {},
            "工艺流程综合题": {},
            "化工流程题": {
              "children": {
                "物质制备类": {}
              }
            },
            "工业流程综合题": {},
            "化学工艺流程题": {},
            "圆锥曲线": {
              "children": {
                "椭圆综合大题": {}
              }
            }
          }
        },
        "非选择题": {
          "children": {
            "生态系统综合题": {},
            "填空题": {
              "children": {
                "生态系统综合考查": {},
                "生态系统综合题": {}
              }
            },
            "材料分析题": {},
            "生态综合解答题": {},
            "生态综合类": {},
            "多选类": {},
            "填空类": {},
            "工业工艺流程题": {},
            "工业流程题": {
              "children": {
                "铬盐制备流程": {}
              }
            },
            "工业流程大题": {},
            "电化学与工艺流程综合题": {},
            "工业流程综合题": {
              "children": {
                "结合滴定实验考查": {}
              }
            }
          }
        },
        "生物": {
          "children": {
            "表格数据分析类习题": {}
          }
        },
        "模考题": {
          "children": {
            "地方二模": {
              "children": {
                "辽宁沈阳二模": {}
              }
            }
          }
        },
        "实验题": {
          "children": {
            "图表信息分析题": {}
          }
        },
        "简答题": {
          "children": {
            "词句作用分析": {},
            "跨材料观点对比探究": {},
            "文本信息整合分析": {},
            "论证思路分析": {},
            "开放探究题": {},
            "文本分析类": {}
          }
        },
        "现代文阅读题": {
          "children": {
            "非连续性文本阅读": {},
            "散文阅读": {
              "children": {
                "单项选择题": {},
                "探究类主观题": {},
                "内容概括主观题": {},
                "行文思路分析题": {},
                "内容赏析题": {},
                "标题作用分析题": {},
                "简答题": {}
              }
            },
            "简答题": {
              "children": {
                "内容探究类": {},
                "情感分析类": {},
                "线索分析": {},
                "作用分析": {}
              }
            },
            "单项选择题": {}
          }
        },
        "现代文阅读": {
          "children": {
            "非连续性多文本阅读": {},
            "散文阅读": {}
          }
        },
        "阅读题": {
          "children": {
            "论述类文本阅读": {}
          }
        },
        "主观题": {
          "children": {
            "文本探究题": {}
          }
        },
        "填空题": {
          "children": {
            "高考真题": {
              "children": {
                "解三角形计算": {},
                "解三角形求值": {},
                "计算类": {}
              }
            },
            "解三角形计算": {},
            "文科数学": {},
            "三角函数计算": {},
            "化工流程综合题": {}
          }
        },
        "图表分析题": {
          "children": {
            "分布分数曲线题": {}
          }
        }
      }
    },
    "难度": {
      "children": {
        "基础": {
          "children": {
            "概念辨析类": {},
            "教材识记类": {},
            "概念理解辨析类": {},
            "多考点综合应用": {},
            "公式直接应用": {},
            "单一考点应用": {},
            "双考点综合": {},
            "单考点应用": {},
            "多知识点综合应用": {},
            "简单运算类": {},
            "多公式综合应用": {}
          }
        },
        "中档": {
          "children": {
            "概念辨析类": {},
            "数据计算类": {},
            "多考点综合": {
              "children": {
                "易混概念辨析": {},
                "含图表分析": {},
                "图表分析": {},
                "高考真题": {},
                "含定量计算": {}
              }
            },
            "高考真题": {
              "children": {
                "多考点综合": {},
                "双小问综合": {},
                "多小问综合": {}
              }
            },
            "多个基础考点综合": {},
            "高考真题类": {},
            "易混淆群落垂直与水平结构": {},
            "需结合材料提取信息作答": {},
            "多个生态考点综合": {},
            "多考点综合应用": {},
            "图表信息提取类": {},
            "图表数据结合考点考查": {},
            "图表信息提取": {},
            "易混概念辨析": {},
            "易混概念辨析+实验数据综合": {},
            "多考点综合考查": {},
            "多文本综合考查": {},
            "主客观题型综合考查": {},
            "多题型多考点综合": {},
            "多步运算": {},
            "公式综合应用": {},
            "高考常规考点综合": {},
            "隐含三角形构成条件验证陷阱": {},
            "多知识点综合": {},
            "2个考点综合": {},
            "多公式综合运算": {},
            "多公式综合化简": {},
            "多公式综合应用": {},
            "双小问综合": {},
            "多模块考点综合": {},
            "多平衡常数综合运算": {}
          }
        },
        "容易": {
          "children": {
            "概念判断类": {},
            "公式直接应用": {},
            "基础公式应用": {}
          }
        },
        "较难": {
          "children": {
            "高考真题": {
              "children": {
                "多模块综合": {},
                "多考点综合": {
                  "children": {
                    "图像分析类": {}
                  }
                }
              }
            },
            "多考点综合": {
              "children": {
                "图像分析": {},
                "图像分析与计算结合": {},
                "图像信息提取": {}
              }
            },
            "高考真题多考点综合": {},
            "多小问多考点综合": {}
          }
        }
      }
    },
    "能力素养": {
      "children": {
        "生物": {
          "children": {
            "科学思维": {
              "children": {
                "概念判断": {},
                "信息提取与判断": {},
                "信息提取与计算": {},
                "分析判断": {},
                "概念辨析": {},
                "逻辑推理": {},
                "信息提取与分析": {},
                "逻辑推理判断": {},
                "图表信息分析": {},
                "模型分析": {},
                "图表信息提取与分析": {},
                "理解应用": {},
                "信息提取与正误判断": {},
                "实例分析与判断": {},
                "概念区分": {},
                "概念辨析应用": {},
                "信息提取与辨析": {},
                "信息提取与整合能力": {},
                "信息提取与逻辑推理": {},
                "概念理解": {},
                "信息分析判断": {},
                "图表数据分析": {},
                "信息提取与逻辑判断": {},
                "数据计算与分析": {},
                "信息获取与分析判断": {},
                "归纳与概括": {},
                "信息提取与应用": {}
              }
            },
            "生命观念": {
              "children": {
                "生态观": {},
                "稳态与平衡观": {},
                "能量观": {},
                "物质能量观": {},
                "物质与能量观": {},
                "生态保护认知": {},
                "结构与功能观": {},
                "生态平衡观念": {},
                "进化与适应观": {}
              }
            },
            "思维": {
              "children": {
                "概念判断": {}
              }
            },
            "社会责任": {
              "children": {
                "生态环境保护认知": {},
                "生态保护意识": {},
                "生产实践应用": {},
                "生态保护认知": {},
                "生态保护意识考查": {},
                "生态环境保护意识": {},
                "生态文明建设认知": {},
                "生态保护应用": {},
                "生态环境保护应用": {},
                "有害生物防治应用": {}
              }
            },
            "科学探究": {
              "children": {
                "问题解释与表达": {},
                "实验结果分析": {},
                "调查方法实践应用": {},
                "对照实验设计分析": {},
                "实验结论阐释": {},
                "实验结果分析与预测": {}
              }
            }
          }
        },
        "化学": {
          "children": {
            "科学态度与社会责任": {
              "children": {
                "生态环境保护意识": {}
              }
            },
            "变化观念与平衡思想": {
              "children": {
                "平衡常数应用": {},
                "平衡移动与浓度变化分析": {}
              }
            },
            "证据推理与模型认知": {
              "children": {
                "图像信息加工": {},
                "图像数据分析": {}
              }
            },
            "宏观辨识与微观探析": {},
            "思维": {
              "children": {
                "流程综合分析": {},
                "综合分析能力": {},
                "综合推理分析": {},
                "定量计算能力": {},
                "证据推理与模型认知": {},
                "逻辑推理": {},
                "信息处理与计算能力": {}
              }
            },
            "科学探究与创新意识": {},
            "科学思维与应用": {},
            "科学思维": {
              "children": {
                "工艺流程综合分析": {}
              }
            },
            "信息获取与加工能力": {},
            "图表信息提取与分析": {},
            "综合分析能力": {},
            "科学探究": {}
          }
        },
        "语文": {
          "children": {
            "思维发展与提升": {
              "children": {
                "文本分析": {},
                "文本逻辑分析": {},
                "文本解读能力": {}
              }
            },
            "信息筛选与整合能力": {},
            "逻辑推理与论证分析能力": {},
            "语言建构与运用": {
              "children": {
                "文本内容理解": {}
              }
            },
            "信息筛选与整合": {},
            "文化传承与理解": {
              "children": {
                "传统文化当代价值阐释": {},
                "劳动价值认知": {},
                "红色文化认知": {}
              }
            },
            "逻辑推理与判断": {},
            "逻辑推理与分析能力": {},
            "审美鉴赏与创造": {
              "children": {
                "散文意象把握": {}
              }
            },
            "语言表达与运用能力": {},
            "文本理解与分析能力": {},
            "文本解读能力": {},
            "积累": {
              "children": {
                "文学鉴赏经验运用": {}
              }
            },
            "思维": {
              "children": {
                "文本逻辑梳理能力": {}
              }
            }
          }
        },
        "数学": {
          "children": {
            "逻辑推理": {},
            "数学运算": {},
            "运算求解": {},
            "运算求解能力": {},
            "逻辑推理能力": {},
            "思维": {},
            "信息提取与应用": {},
            "直观想象": {}
          }
        },
        "思维": {
          "children": {
            "逻辑推理": {},
            "逻辑推理能力": {}
          }
        }
      }
    },
    "思维": {},
    "语文": {},
    "数学": {},
    "测试1": {
      "children": {
        "测试2": {}
      }
    },
    "打印": {
      "children": {
        "数学": {
          "children": {
            "原三角函数": {},
            "一4/5": {}
          }
        }
      }
    },
    "化学": {}
  }
}